{"owner_type":"orgs","package_type":"container","owner_id":"30164233","owner":"telekom-security","repo":"tpotce","package":"medpot","date":"2024-07-19","size":"16.2 MB","versions":"28","tagged":"3","downloads":"16.5k","downloads_month":"356","downloads_week":"61","downloads_day":"55","raw_size":16235208,"raw_versions":28,"raw_tagged":3,"raw_downloads":16579,"raw_downloads_month":356,"raw_downloads_week":61,"raw_downloads_day":55,"version":[{"id":232329492,"name":"sha256:d69a00a6146d1ebec1b397576f8a1433f0e9ef763c3a4db1dff611ec49676e8e","date":"2024-07-19","newest":true,"size":"16.2 MB","downloads":"15","downloads_month":"15","downloads_week":"3","downloads_day":"2","raw_size":16235208,"raw_downloads":15,"raw_downloads_month":15,"raw_downloads_week":3,"raw_downloads_day":2,"tags":[""]},{"id":232329486,"name":"sha256:b96dcc4ed5df58b9f126ddbd2665d84503d6bee889bb5e0de1e2241afb13de11","date":"2024-07-19","newest":false,"size":"2.1 kB","downloads":"12","downloads_month":"12","downloads_week":"2","downloads_day":"2","raw_size":2177,"raw_downloads":12,"raw_downloads_month":12,"raw_downloads_week":2,"raw_downloads_day":2,"tags":[""]},{"id":232329479,"name":"sha256:fe816f381cb99d179aa2c10146743870cd781157d14cc691c522a17fb2b9cc4b","date":"2024-07-19","newest":false,"size":"2.1 kB","downloads":"12","downloads_month":"12","downloads_week":"2","downloads_day":"2","raw_size":2177,"raw_downloads":12,"raw_downloads_month":12,"raw_downloads_week":2,"raw_downloads_day":2,"tags":[""]},{"id":232329475,"name":"sha256:157bf9f652dc32b9ff02908efb7896256bdc7dca43a9523e3b99638f04c41e92","date":"2024-07-19","newest":false,"size":"7.9 MB","downloads":"12","downloads_month":"12","downloads_week":"2","downloads_day":"2","raw_size":7935058,"raw_downloads":12,"raw_downloads_month":12,"raw_downloads_week":2,"raw_downloads_day":2,"tags":[""]},{"id":232329469,"name":"sha256:e1ca7abe68736015c03ba2e9adcac87ed8b7e8017e78d7e8df916f44d583d234","date":"2024-07-19","newest":false,"size":"8.2 MB","downloads":"16","downloads_month":"16","downloads_week":"3","downloads_day":"2","raw_size":8295796,"raw_downloads":16,"raw_downloads_month":16,"raw_downloads_week":3,"raw_downloads_day":2,"tags":[""]},{"id":195080078,"name":"sha256:d76e750bd2d64f943017f326e973344969a976c099a1620e6257d8539352fe03","date":"2024-07-19","newest":false,"size":"16.2 MB","downloads":"71","downloads_month":"12","downloads_week":"2","downloads_day":"2","raw_size":16232833,"raw_downloads":71,"raw_downloads_month":12,"raw_downloads_week":2,"raw_downloads_day":2,"tags":[""]},{"id":195080076,"name":"sha256:d66ca140468ad3be5fb3a1b22108735967e6b7ce27cb1e347311178c0dc57c3a","date":"2024-07-19","newest":false,"size":"2.1 kB","downloads":"12","downloads_month":"12","downloads_week":"2","downloads_day":"2","raw_size":2177,"raw_downloads":12,"raw_downloads_month":12,"raw_downloads_week":2,"raw_downloads_day":2,"tags":[""]},{"id":195080074,"name":"sha256:7db597753bf1d639fdcb520be2235c5f3f01693838745a96fdbe43cc6cedc541","date":"2024-07-19","newest":false,"size":"2.1 kB","downloads":"12","downloads_month":"12","downloads_week":"2","downloads_day":"2","raw_size":2177,"raw_downloads":12,"raw_downloads_month":12,"raw_downloads_week":2,"raw_downloads_day":2,"tags":[""]},{"id":195080072,"name":"sha256:6b513f95b17fb4cddb6cc0055c100e3f1b178c35f12616df3d80e538022b1d64","date":"2024-07-19","newest":false,"size":"7.9 MB","downloads":"16","downloads_month":"12","downloads_week":"2","downloads_day":"2","raw_size":7933506,"raw_downloads":16,"raw_downloads_month":12,"raw_downloads_week":2,"raw_downloads_day":2,"tags":[""]},{"id":195080070,"name":"sha256:34c77329751fb1b32b05da106cf56f2afdcc0a950e42a2de5d36490e5b71e569","date":"2024-07-19","newest":false,"size":"8.2 MB","downloads":"34","downloads_month":"12","downloads_week":"2","downloads_day":"2","raw_size":8294973,"raw_downloads":34,"raw_downloads_month":12,"raw_downloads_week":2,"raw_downloads_day":2,"tags":[""]},{"id":190048905,"name":"sha256:f30d77bdffd4188e96bb79e1b6b2df43d827a33c1b0416f9de274eacd78ff1f8","date":"2024-07-19","newest":false,"size":"16.2 MB","downloads":"54","downloads_month":"13","downloads_week":"3","downloads_day":"2","raw_size":16232861,"raw_downloads":54,"raw_downloads_month":13,"raw_downloads_week":3,"raw_downloads_day":2,"tags":[""]},{"id":190048895,"name":"sha256:9f8fa9323206ef1768cbd4bdb8388dc19fcece7dc00ee7debf3a65b6d7cf8dd9","date":"2024-07-19","newest":false,"size":"2.1 kB","downloads":"12","downloads_month":"12","downloads_week":"2","downloads_day":"2","raw_size":2177,"raw_downloads":12,"raw_downloads_month":12,"raw_downloads_week":2,"raw_downloads_day":2,"tags":[""]},{"id":190048889,"name":"sha256:aaead62fa5dc4eb1cb14028e8bd0ed865fcd2e7b412c61f401b63c35c43297f2","date":"2024-07-19","newest":false,"size":"7.9 MB","downloads":"12","downloads_month":"12","downloads_week":"2","downloads_day":"2","raw_size":7933524,"raw_downloads":12,"raw_downloads_month":12,"raw_downloads_week":2,"raw_downloads_day":2,"tags":[""]},{"id":190048881,"name":"sha256:7ecacc43e73b7510b538d46797bfded83a14a953c7dc071e9365353e46e8165c","date":"2024-07-19","newest":false,"size":"2.1 kB","downloads":"12","downloads_month":"12","downloads_week":"2","downloads_day":"2","raw_size":2177,"raw_downloads":12,"raw_downloads_month":12,"raw_downloads_week":2,"raw_downloads_day":2,"tags":[""]},{"id":190048877,"name":"sha256:3916a1cdab93c70d4eb498c16496bbde6ef52ed30ca7fcdcfa7ffbd18fae8ccf","date":"2024-07-19","newest":false,"size":"8.2 MB","downloads":"13","downloads_month":"13","downloads_week":"3","downloads_day":"2","raw_size":8294983,"raw_downloads":13,"raw_downloads_month":13,"raw_downloads_week":3,"raw_downloads_day":2,"tags":[""]},{"id":179112227,"name":"sha256:5f0fd6684ff9b934dec9d864405895dbdf27ac8893d2a63e8a87bacb3ce821af","date":"2024-07-19","newest":false,"size":"19.1 MB","downloads":"21","downloads_month":"12","downloads_week":"2","downloads_day":"2","raw_size":19116253,"raw_downloads":21,"raw_downloads_month":12,"raw_downloads_week":2,"raw_downloads_day":2,"tags":[""]},{"id":179112225,"name":"sha256:5d7cd1a97aff3791eac06cdc4fe149844c1196522cd91d57f20a3a3ec598bbc6","date":"2024-07-19","newest":false,"size":"2 kB","downloads":"12","downloads_month":"12","downloads_week":"2","downloads_day":"2","raw_size":2026,"raw_downloads":12,"raw_downloads_month":12,"raw_downloads_week":2,"raw_downloads_day":2,"tags":[""]},{"id":179112219,"name":"sha256:ab43787191e782043b2f4d4726413be0aa34b00a91a6f1f7e615c8c0a9149570","date":"2024-07-19","newest":false,"size":"2 kB","downloads":"12","downloads_month":"12","downloads_week":"2","downloads_day":"2","raw_size":2026,"raw_downloads":12,"raw_downloads_month":12,"raw_downloads_week":2,"raw_downloads_day":2,"tags":[""]},{"id":179085075,"name":"sha256:3b7e572ebb7b08675f7097a53949ea88d5c1d1a415552d994c07addef36ef310","date":"2024-07-19","newest":false,"size":"19.1 MB","downloads":"13","downloads_month":"12","downloads_week":"2","downloads_day":"2","raw_size":19116255,"raw_downloads":13,"raw_downloads_month":12,"raw_downloads_week":2,"raw_downloads_day":2,"tags":[""]},{"id":179085072,"name":"sha256:1c40b80ade56321fb2fc8a211fb37ab3b5fb7d4c8dbecbc732c5fd319c32faef","date":"2024-07-19","newest":false,"size":"2 kB","downloads":"11","downloads_month":"11","downloads_week":"1","downloads_day":"1","raw_size":2027,"raw_downloads":11,"raw_downloads_month":11,"raw_downloads_week":1,"raw_downloads_day":1,"tags":[""]},{"id":179085069,"name":"sha256:dd608b834e80a818d5c1c7a8fe52d412bec2089364e0bf72a0cc82f9e8b08500","date":"2024-07-19","newest":false,"size":"9.3 MB","downloads":"18","downloads_month":"17","downloads_week":"2","downloads_day":"2","raw_size":9316980,"raw_downloads":18,"raw_downloads_month":17,"raw_downloads_week":2,"raw_downloads_day":2,"tags":[""]},{"id":179085063,"name":"sha256:486d87fe766ab5ccf700758a7e4e3ec9b91e6aa257617724563f93d0091e3f3f","date":"2024-07-19","newest":false,"size":"9.7 MB","downloads":"18","downloads_month":"18","downloads_week":"3","downloads_day":"3","raw_size":9795221,"raw_downloads":18,"raw_downloads_month":18,"raw_downloads_week":3,"raw_downloads_day":3,"tags":[""]},{"id":179085058,"name":"sha256:0139bf68695a7d8354bfbdf5680f24744060321c4ebfb714415f183ea8fd4803","date":"2024-07-19","newest":false,"size":"2 kB","downloads":"11","downloads_month":"11","downloads_week":"1","downloads_day":"1","raw_size":2027,"raw_downloads":11,"raw_downloads_month":11,"raw_downloads_week":1,"raw_downloads_day":1,"tags":[""]},{"id":105685433,"name":"sha256:bb6c1c2447ebbe525c9cf3d042056db003c2991936fabdcba9b9b1cbde9efa1e","date":"2024-07-19","newest":false,"size":"18.9 MB","downloads":"83","downloads_month":"13","downloads_week":"3","downloads_day":"2","raw_size":18998467,"raw_downloads":83,"raw_downloads_month":13,"raw_downloads_week":3,"raw_downloads_day":2,"tags":[""]},{"id":105685430,"name":"sha256:4eeeea4b7c8578a1098ad59775c7cae31f00dbf5fe2e43b0bebf4cdaaa0aec5b","date":"2024-07-19","newest":false,"size":"2 kB","downloads":"12","downloads_month":"12","downloads_week":"2","downloads_day":"2","raw_size":2017,"raw_downloads":12,"raw_downloads_month":12,"raw_downloads_week":2,"raw_downloads_day":2,"tags":[""]},{"id":105685426,"name":"sha256:fb34ca2213f74ecab170f386a033b38fc1c0156a9305e1aef9c24f226169d4b0","date":"2024-07-19","newest":false,"size":"9.2 MB","downloads":"69","downloads_month":"12","downloads_week":"2","downloads_day":"2","raw_size":9263302,"raw_downloads":69,"raw_downloads_month":12,"raw_downloads_week":2,"raw_downloads_day":2,"tags":[""]},{"id":105685422,"name":"sha256:07cec64749415b54734421571fc87d2542121c743660306e0fa3d50463616606","date":"2024-07-19","newest":false,"size":"9.7 MB","downloads":"27","downloads_month":"13","downloads_week":"3","downloads_day":"2","raw_size":9731131,"raw_downloads":27,"raw_downloads_month":13,"raw_downloads_week":3,"raw_downloads_day":2,"tags":[""]},{"id":105685418,"name":"sha256:b24ed2f63312c31eb10f5eafd7b17fa3a6dff0585356d83782eefed7cd839bd4","date":"2024-07-19","newest":false,"size":"2 kB","downloads":"12","downloads_month":"12","downloads_week":"2","downloads_day":"2","raw_size":2017,"raw_downloads":12,"raw_downloads_month":12,"raw_downloads_week":2,"raw_downloads_day":2,"tags":[""]}]}
