{"owner_type":"orgs","package_type":"container","owner_id":370544,"owner":"NetApp","repo":"harvest","package":"harvest","date":"2026-04-20","size":"32.5 MB","versions":"30","tagged":"27","owner_rank":"1","repo_rank":"1","downloads":"308.9k","downloads_month":"10.2k","downloads_week":"1.9k","downloads_day":"131","raw_size":32550846,"raw_versions":30,"raw_tagged":27,"raw_owner_rank":1,"raw_repo_rank":1,"raw_downloads":308933,"raw_downloads_month":10266,"raw_downloads_week":1941,"raw_downloads_day":131,"version":[{"id":120474867,"name":"sha256:f21e787bd33e885bd1fb3180496e1755271601df43f47da19b69ed9e3cc6d06d","date":"2026-04-20","newest":false,"latest":false,"size":"27.1 MB","downloads":"2.9k","downloads_month":"42","downloads_week":"2","downloads_day":"0","raw_size":27140056,"raw_downloads":2905,"raw_downloads_month":42,"raw_downloads_week":2,"raw_downloads_day":0,"tags":["23.08.0-1"]},{"id":147103547,"name":"sha256:f68ad9d4144f0338a2f0878bb6b29249c91835d73e5c01d1662ef00c48b1e083","date":"2026-04-20","newest":false,"latest":false,"size":"27.3 MB","downloads":"16k","downloads_month":"74","downloads_week":"2","downloads_day":"0","raw_size":27387382,"raw_downloads":16039,"raw_downloads_month":74,"raw_downloads_week":2,"raw_downloads_day":0,"tags":["23.11.0-1"]},{"id":181744544,"name":"sha256:64adc05823d0a09f9f49bac34d6057dce5b037d17c4860ccd93001b12909aef9","date":"2026-04-20","newest":false,"latest":false,"size":"28 MB","downloads":"4.3k","downloads_month":"47","downloads_week":"3","downloads_day":"0","raw_size":28074141,"raw_downloads":4368,"raw_downloads_month":47,"raw_downloads_week":3,"raw_downloads_day":0,"tags":["24.02.0-1"]},{"id":218429491,"name":"sha256:5ab5e9907cf735269a7ec9636ccfea7b1f38a864314782e9c2ff8490e264b00c","date":"2026-04-20","newest":false,"latest":false,"size":"27.9 MB","downloads":"1.1k","downloads_month":"47","downloads_week":"2","downloads_day":"0","raw_size":27923402,"raw_downloads":1189,"raw_downloads_month":47,"raw_downloads_week":2,"raw_downloads_day":0,"tags":["24.05.0-1"]},{"id":222495685,"name":"sha256:2dd408172428caf557b30b9f1a7145340d22f1e04f946d1b944dbfa4b1598840","date":"2026-04-20","newest":false,"latest":false,"size":"27.9 MB","downloads":"33k","downloads_month":"43","downloads_week":"3","downloads_day":"0","raw_size":27927065,"raw_downloads":33091,"raw_downloads_month":43,"raw_downloads_week":3,"raw_downloads_day":0,"tags":["24.05.1-1"]},{"id":229566205,"name":"sha256:979f920f1de5a8ebdd534c79f14da125c8bb162a3cc3b107b011c9c6c396c453","date":"2026-04-20","newest":false,"latest":false,"size":"28 MB","downloads":"25.3k","downloads_month":"42","downloads_week":"2","downloads_day":"0","raw_size":28028415,"raw_downloads":25311,"raw_downloads_month":42,"raw_downloads_week":2,"raw_downloads_day":0,"tags":["24.05.2-1"]},{"id":256737527,"name":"sha256:9292d5556d8b0e78178a37fa698a48ed8f77ae1b79a33849c6398651e2afe06a","date":"2026-04-20","newest":false,"latest":false,"size":"27.9 MB","downloads":"46.8k","downloads_month":"51","downloads_week":"5","downloads_day":"0","raw_size":27947784,"raw_downloads":46892,"raw_downloads_month":51,"raw_downloads_week":5,"raw_downloads_day":0,"tags":["24.08.0-1"]},{"id":301313024,"name":"sha256:a2d0fff53c4ff05ee082bcf1dd19d9682f5975a56ca7e779bc4710775d2738b8","date":"2026-04-20","newest":false,"latest":false,"size":"34 MB","downloads":"818","downloads_month":"42","downloads_week":"2","downloads_day":"0","raw_size":34040474,"raw_downloads":818,"raw_downloads_month":42,"raw_downloads_week":2,"raw_downloads_day":0,"tags":["24.11.0-1-fips"]},{"id":301313218,"name":"sha256:49af77a171d76c1f54ad255eb23d06106a3463dd110cc90e55dc40b63f256214","date":"2026-04-20","newest":false,"latest":false,"size":"29.9 MB","downloads":"8.3k","downloads_month":"42","downloads_week":"2","downloads_day":"0","raw_size":29972458,"raw_downloads":8341,"raw_downloads_month":42,"raw_downloads_week":2,"raw_downloads_day":0,"tags":["24.11.0-1"]},{"id":311670408,"name":"sha256:c645f8eaf29d3acc46b10400554772e9a005afd0a1720ec17820db368f3e53f0","date":"2026-04-20","newest":false,"latest":false,"size":"34.1 MB","downloads":"822","downloads_month":"42","downloads_week":"2","downloads_day":"0","raw_size":34182209,"raw_downloads":822,"raw_downloads_month":42,"raw_downloads_week":2,"raw_downloads_day":0,"tags":["24.11.1-1-fips"]},{"id":311670491,"name":"sha256:9d0659ca06b05704b9c1d87847b24b48bb1c150cbd8933a12ffe44390e70a082","date":"2026-04-20","newest":false,"latest":false,"size":"30.1 MB","downloads":"17.1k","downloads_month":"70","downloads_week":"11","downloads_day":"1","raw_size":30115489,"raw_downloads":17189,"raw_downloads_month":70,"raw_downloads_week":11,"raw_downloads_day":1,"tags":["24.11.1-1"]},{"id":355104156,"name":"sha256:c24563ef800a3296eb354a103312b27dfd4f690fe2e0e965516ca57fddf2c83a","date":"2026-04-20","newest":false,"latest":false,"size":"30.5 MB","downloads":"823","downloads_month":"42","downloads_week":"2","downloads_day":"0","raw_size":30585816,"raw_downloads":823,"raw_downloads_month":42,"raw_downloads_week":2,"raw_downloads_day":0,"tags":["25.02.0-1-fips"]},{"id":355104310,"name":"sha256:9d37d56bdb9604f332e8f8de0535d5a33ab25819cba12c6a1cc6c30fbcec22aa","date":"2026-04-20","newest":false,"latest":false,"size":"30.5 MB","downloads":"16.4k","downloads_month":"239","downloads_week":"44","downloads_day":"6","raw_size":30585754,"raw_downloads":16435,"raw_downloads_month":239,"raw_downloads_week":44,"raw_downloads_day":6,"tags":["25.02.0-1"]},{"id":418724626,"name":"sha256:3a5b078738846425dd0f888a2ed85d72962c7de9276184e53e403f49d66ccbec","date":"2026-04-20","newest":false,"latest":false,"size":"31.6 MB","downloads":"798","downloads_month":"42","downloads_week":"2","downloads_day":"0","raw_size":31699474,"raw_downloads":798,"raw_downloads_month":42,"raw_downloads_week":2,"raw_downloads_day":0,"tags":["25.05.0-1-fips"]},{"id":418724751,"name":"sha256:1c848b59fbed33b93cae7a0f5417863faf49133cb3b747458081bb29ff2de7d5","date":"2026-04-20","newest":false,"latest":false,"size":"31.6 MB","downloads":"7.8k","downloads_month":"74","downloads_week":"9","downloads_day":"1","raw_size":31699408,"raw_downloads":7807,"raw_downloads_month":74,"raw_downloads_week":9,"raw_downloads_day":1,"tags":["25.05.0-1"]},{"id":434096524,"name":"sha256:af6175f3f006fb21719157c6b186eb50ca376070e61b4c802258dc21c0680e72","date":"2026-04-20","newest":false,"latest":false,"size":"31.6 MB","downloads":"888","downloads_month":"42","downloads_week":"2","downloads_day":"0","raw_size":31670357,"raw_downloads":888,"raw_downloads_month":42,"raw_downloads_week":2,"raw_downloads_day":0,"tags":["25.05.1-1-fips"]},{"id":434096599,"name":"sha256:e299c73a45be1abb71802a1d0f360642ad3bc617921e6bad4363329da8952d17","date":"2026-04-20","newest":false,"latest":false,"size":"31.6 MB","downloads":"8.2k","downloads_month":"132","downloads_week":"23","downloads_day":"3","raw_size":31670277,"raw_downloads":8231,"raw_downloads_month":132,"raw_downloads_week":23,"raw_downloads_day":3,"tags":["25.05.1-1"]},{"id":485973007,"name":"sha256:c2e4e92c626d1f91156a2681f6241b4986d4227003c7f43d88865e978d534c49","date":"2026-04-20","newest":false,"latest":false,"size":"31.9 MB","downloads":"710","downloads_month":"42","downloads_week":"2","downloads_day":"0","raw_size":31933979,"raw_downloads":710,"raw_downloads_month":42,"raw_downloads_week":2,"raw_downloads_day":0,"tags":["25.08.0-1-fips"]},{"id":485973118,"name":"sha256:08855b7fdabd6d46ce75982a6f3112f038b33f397b2a96622ac26c9d45e51736","date":"2026-04-20","newest":false,"latest":false,"size":"31.9 MB","downloads":"1.3k","downloads_month":"42","downloads_week":"2","downloads_day":"0","raw_size":31933947,"raw_downloads":1335,"raw_downloads_month":42,"raw_downloads_week":2,"raw_downloads_day":0,"tags":["25.08.0-1"]},{"id":489695931,"name":"sha256:1bba1ec3280b4421e80950d1f9257ae22ba66e66deed5ad3b50ee42369cea9eb","date":"2026-04-20","newest":false,"latest":false,"size":"31.9 MB","downloads":"914","downloads_month":"42","downloads_week":"2","downloads_day":"0","raw_size":31932496,"raw_downloads":914,"raw_downloads_month":42,"raw_downloads_week":2,"raw_downloads_day":0,"tags":["25.08.1-1-fips"]},{"id":489696136,"name":"sha256:32eb2624797d2fcab4a0352f0d4e1c54ccec7e497121fa0929226ea76ea5cdd5","date":"2026-04-20","newest":false,"latest":false,"size":"31.9 MB","downloads":"19.1k","downloads_month":"148","downloads_week":"23","downloads_day":"1","raw_size":31932459,"raw_downloads":19172,"raw_downloads_month":148,"raw_downloads_week":23,"raw_downloads_day":1,"tags":["25.08.1-1"]},{"id":571737982,"name":"sha256:16bb32cee9c9f4329567aed57561ed0d0b852f4504f573e7312d9bb9e6dcf19e","date":"2026-04-20","newest":false,"latest":false,"size":"31.3 MB","downloads":"680","downloads_month":"42","downloads_week":"2","downloads_day":"0","raw_size":31375072,"raw_downloads":680,"raw_downloads_month":42,"raw_downloads_week":2,"raw_downloads_day":0,"tags":["25.11.0-1-fips"]},{"id":571738225,"name":"sha256:e9bce8b7ba0d67ef26bda7a41538811dc1002329fc8b4eccaf6b136fe1b25d51","date":"2026-04-20","newest":false,"latest":false,"size":"31.3 MB","downloads":"70.6k","downloads_month":"951","downloads_week":"185","downloads_day":"13","raw_size":31375018,"raw_downloads":70622,"raw_downloads_month":951,"raw_downloads_week":185,"raw_downloads_day":13,"tags":["25.11.0-1"]},{"id":688647135,"name":"sha256:5344f7af402002088836b99b9a0d80b83e9bb65953750fa02790253421c3b6f9","date":"2026-04-20","newest":false,"latest":false,"size":"32.3 MB","downloads":"306","downloads_month":"80","downloads_week":"3","downloads_day":"0","raw_size":32350543,"raw_downloads":306,"raw_downloads_month":80,"raw_downloads_week":3,"raw_downloads_day":0,"tags":["26.02.0-1-fips","latest-fips"]},{"id":688647336,"name":"sha256:3ce73a944c5d97bca011c376cd18df72339eaa9e1a8fbe149b579e96832e1685","date":"2026-04-20","newest":false,"latest":true,"size":"32.3 MB","downloads":"18k","downloads_month":"7.8k","downloads_week":"1.6k","downloads_day":"106","raw_size":32350471,"raw_downloads":18068,"raw_downloads_month":7806,"raw_downloads_week":1604,"raw_downloads_day":106,"tags":["26.02.0-1","latest"]},{"id":805420790,"name":"sha256:ec0568729952af7dc431f0e3b161d3770b048530cb53e5d44f5e2d818ee909d1","date":"2026-04-20","newest":false,"latest":false,"size":"32.5 MB","downloads":"0","downloads_month":"0","downloads_week":"0","downloads_day":"0","raw_size":32550917,"raw_downloads":0,"raw_downloads_month":0,"raw_downloads_week":0,"raw_downloads_day":0,"tags":[]},{"id":806613856,"name":"sha256:5cdffe33ec6f3a10293ee74408e8c701e2ea9bdcba3ec04705e9469df6a48050","date":"2026-04-20","newest":false,"latest":false,"size":"32.5 MB","downloads":"0","downloads_month":"0","downloads_week":"0","downloads_day":"0","raw_size":32550971,"raw_downloads":0,"raw_downloads_month":0,"raw_downloads_week":0,"raw_downloads_day":0,"tags":[]},{"id":806613921,"name":"sha256:44579e449d91178c66eafe79b139a1e3de7e62371d0be5683a552ac3a62d18f0","date":"2026-04-20","newest":false,"latest":false,"size":"32.5 MB","downloads":"0","downloads_month":"0","downloads_week":"0","downloads_day":"0","raw_size":32550869,"raw_downloads":0,"raw_downloads_month":0,"raw_downloads_week":0,"raw_downloads_day":0,"tags":[]},{"id":807988715,"name":"sha256:dbb3561aff897e5d88fe7ea1a1a97320c2690bc7b3fd85f51bf816cd8a40fbe8","date":"2026-04-20","newest":false,"latest":false,"size":"32.5 MB","downloads":"0","downloads_month":"0","downloads_week":"0","downloads_day":"0","raw_size":32550893,"raw_downloads":0,"raw_downloads_month":0,"raw_downloads_week":0,"raw_downloads_day":0,"tags":["nightly-fips"]},{"id":807989865,"name":"sha256:ac48d0d24ec36c90df500e4285baad0024a9dc9110cf1a704cfada5fe7dbc8a2","date":"2026-04-20","newest":true,"latest":false,"size":"32.5 MB","downloads":"0","downloads_month":"0","downloads_week":"0","downloads_day":"0","raw_size":32550846,"raw_downloads":0,"raw_downloads_month":0,"raw_downloads_week":0,"raw_downloads_day":0,"tags":["nightly"]}]}
