{"owner_type":"orgs","package_type":"container","owner_id":916280,"owner":"bcgov","repo":"cas-registration","package":"cas-reg-backend","date":"2026-06-22","size":"269.4 MB","versions":"60","tagged":"57","owner_rank":"21","repo_rank":"1","downloads":"1.2M","downloads_month":"2.2k","downloads_week":"2.2k","downloads_day":"253","raw_size":269499913,"raw_versions":60,"raw_tagged":57,"raw_owner_rank":21,"raw_repo_rank":1,"raw_downloads":1205787,"raw_downloads_month":2252,"raw_downloads_week":2252,"raw_downloads_day":253,"version":[{"id":956328031,"name":"sha256:e9a35ae76ff2247cc4bda60d748059168d317ec26a5a8fec35188bcfd40ec49c","date":"2026-06-22","newest":false,"latest":false,"size":"269.4 MB","downloads":"5","downloads_month":"5","downloads_week":"5","downloads_day":"0","raw_size":269479753,"raw_downloads":5,"raw_downloads_month":5,"raw_downloads_week":5,"raw_downloads_day":0,"tags":["bcf8ae0e8d2752143b10be81789af318f197db6b"]},{"id":956402619,"name":"sha256:482ac8e8aaccec4f241269aba651b1035ed6876f86976a2ef21245c6f007bacc","date":"2026-06-22","newest":false,"latest":false,"size":"269.4 MB","downloads":"0","downloads_month":"0","downloads_week":"0","downloads_day":"0","raw_size":269481468,"raw_downloads":0,"raw_downloads_month":0,"raw_downloads_week":0,"raw_downloads_day":0,"tags":["957053c4cf76c5ad1a136b61f39f4f6db5761edd"]},{"id":956572716,"name":"sha256:9f190403c40a1d94a9ed45f6585e50afc5ac56972638c6a8bf5b7f807da43967","date":"2026-06-22","newest":false,"latest":false,"size":"269.4 MB","downloads":"0","downloads_month":"0","downloads_week":"0","downloads_day":"0","raw_size":269451867,"raw_downloads":0,"raw_downloads_month":0,"raw_downloads_week":0,"raw_downloads_day":0,"tags":["6ba9f8e3bf8e6a8a2d308752ec3ff855e2fccb61"]},{"id":956580519,"name":"sha256:8c3e93f720f8660b0746abf5445ede23999b568afd185d0678c172d918b31b3a","date":"2026-06-22","newest":false,"latest":false,"size":"269.4 MB","downloads":"0","downloads_month":"0","downloads_week":"0","downloads_day":"0","raw_size":269451060,"raw_downloads":0,"raw_downloads_month":0,"raw_downloads_week":0,"raw_downloads_day":0,"tags":["5ad7e0f27144ec52bf22110150a38f684c288fe8"]},{"id":956585284,"name":"sha256:bd090093147f79fb789fde6a30910d96f3f8fc4256c81d8c0565a8a01fc08d2c","date":"2026-06-22","newest":false,"latest":false,"size":"269.4 MB","downloads":"5","downloads_month":"5","downloads_week":"5","downloads_day":"0","raw_size":269480562,"raw_downloads":5,"raw_downloads_month":5,"raw_downloads_week":5,"raw_downloads_day":0,"tags":["8b09fd3bcf812b2873297d1ac1d00ed14e33c6d8"]},{"id":956596093,"name":"sha256:4351907959f26625063d5093ffe059c8ce32c1e87187e65c544f7b46c7d15909","date":"2026-06-22","newest":false,"latest":false,"size":"269.4 MB","downloads":"0","downloads_month":"0","downloads_week":"0","downloads_day":"0","raw_size":269453065,"raw_downloads":0,"raw_downloads_month":0,"raw_downloads_week":0,"raw_downloads_day":0,"tags":["7b62f2c289397e6d1a0cc6509a6c4a748233c137"]},{"id":956623013,"name":"sha256:b6b1bc1d4d7d3d8e7f480ba703350a4c68bee43fcf2f774f17b8b6d1b76273b6","date":"2026-06-22","newest":false,"latest":false,"size":"269.4 MB","downloads":"0","downloads_month":"0","downloads_week":"0","downloads_day":"0","raw_size":269453066,"raw_downloads":0,"raw_downloads_month":0,"raw_downloads_week":0,"raw_downloads_day":0,"tags":["cb468317551cf0d3ad7e9ad0b956b19d22b904cc"]},{"id":956804576,"name":"sha256:a981b4d21d0d410a0b75949418a2ddb878dd38bdfc57eb8c6ac32a5579e82763","date":"2026-06-22","newest":false,"latest":false,"size":"269.4 MB","downloads":"0","downloads_month":"0","downloads_week":"0","downloads_day":"0","raw_size":269450749,"raw_downloads":0,"raw_downloads_month":0,"raw_downloads_week":0,"raw_downloads_day":0,"tags":["2cc881854f8eb05a0b071ccf9f6b0257fc85ff86"]},{"id":956965015,"name":"sha256:088689f7df7182888d979391ba0f6f325f0dea71c19833a957d8a345a0d8554b","date":"2026-06-22","newest":false,"latest":false,"size":"269.4 MB","downloads":"5","downloads_month":"5","downloads_week":"5","downloads_day":"0","raw_size":269453437,"raw_downloads":5,"raw_downloads_month":5,"raw_downloads_week":5,"raw_downloads_day":0,"tags":["6b90d163300c4925e060fec352ec48a1b637d6e4"]},{"id":956980285,"name":"sha256:06bd2235c718e05a8fa4eb7555a6e97bf773295c9ab4ff28d21b3fa85170f46f","date":"2026-06-22","newest":false,"latest":false,"size":"269.4 MB","downloads":"3","downloads_month":"3","downloads_week":"3","downloads_day":"0","raw_size":269476210,"raw_downloads":3,"raw_downloads_month":3,"raw_downloads_week":3,"raw_downloads_day":0,"tags":["04237290cbb3c8d978b2ff79c21f37a660e5a71d"]},{"id":956994479,"name":"sha256:fb7a170a8e9770dcb06947325ccd24467d33ec364c6cb8be8642ecf50a208c62","date":"2026-06-22","newest":false,"latest":false,"size":"269.4 MB","downloads":"5","downloads_month":"5","downloads_week":"5","downloads_day":"0","raw_size":269478367,"raw_downloads":5,"raw_downloads_month":5,"raw_downloads_week":5,"raw_downloads_day":0,"tags":["0c0d44e774b0879b8d7549eb8f2b5389fecc5c16"]},{"id":957038593,"name":"sha256:c4bd3ef053fb5bb93f8a413935863c179d70ba1e7de85553a5771da54d20becd","date":"2026-06-22","newest":false,"latest":false,"size":"269.4 MB","downloads":"5","downloads_month":"5","downloads_week":"5","downloads_day":"0","raw_size":269479168,"raw_downloads":5,"raw_downloads_month":5,"raw_downloads_week":5,"raw_downloads_day":0,"tags":["27502a6650ef117a7798e18e03db32cf8b8823fd"]},{"id":957139768,"name":"sha256:5eb084f6fb906c0e3d0878a30934798f8966a24edbbd5e838c034ca2ea341149","date":"2026-06-22","newest":false,"latest":false,"size":"269.4 MB","downloads":"0","downloads_month":"0","downloads_week":"0","downloads_day":"0","raw_size":269476074,"raw_downloads":0,"raw_downloads_month":0,"raw_downloads_week":0,"raw_downloads_day":0,"tags":["01816c37845d90ab23ff3405d620d04c97dbc8ca"]},{"id":957141917,"name":"sha256:2ebfe7afe7b43989e41d71e40beb9242d6702a124a38ec6a9fe9cc603bb29748","date":"2026-06-22","newest":false,"latest":false,"size":"269.4 MB","downloads":"0","downloads_month":"0","downloads_week":"0","downloads_day":"0","raw_size":269474326,"raw_downloads":0,"raw_downloads_month":0,"raw_downloads_week":0,"raw_downloads_day":0,"tags":["17628e8c913f5fa9cd8dbfda527360dd9bb3cd73","pr-4826"]},{"id":957165599,"name":"sha256:071362b5d2997aabd6189bb7214002870ffbd7923a2046621cdb12c25f5cb811","date":"2026-06-22","newest":false,"latest":false,"size":"269.4 MB","downloads":"6","downloads_month":"6","downloads_week":"6","downloads_day":"0","raw_size":269476029,"raw_downloads":6,"raw_downloads_month":6,"raw_downloads_week":6,"raw_downloads_day":0,"tags":["457c2349a02f1bf9c33c37df7e586a19574149b0"]},{"id":957178924,"name":"sha256:20e2e9b31d6ba86344207a02b5d70a2c9231c2dc380669bd4a26cab6ab7d6541","date":"2026-06-22","newest":false,"latest":false,"size":"269.4 MB","downloads":"1.2k","downloads_month":"1.2k","downloads_week":"1.2k","downloads_day":"116","raw_size":269444247,"raw_downloads":1222,"raw_downloads_month":1222,"raw_downloads_week":1222,"raw_downloads_day":116,"tags":["8023c9046fb2704828d1a77662ca6e0cc3bdc477"]},{"id":957204379,"name":"sha256:023c119904efe4324397465377d8efd1a31be576ef74eef676f1a4a589203f0e","date":"2026-06-22","newest":false,"latest":false,"size":"269.4 MB","downloads":"0","downloads_month":"0","downloads_week":"0","downloads_day":"0","raw_size":269453835,"raw_downloads":0,"raw_downloads_month":0,"raw_downloads_week":0,"raw_downloads_day":0,"tags":["afd7647ad22a2201a4f32c6ca2a39b8aa6833134"]},{"id":957220242,"name":"sha256:0a5b33e795beeca4039ac5580e7cacd5264f9088b9b725658c791e99c77c63df","date":"2026-06-22","newest":false,"latest":false,"size":"269.4 MB","downloads":"0","downloads_month":"0","downloads_week":"0","downloads_day":"0","raw_size":269483747,"raw_downloads":0,"raw_downloads_month":0,"raw_downloads_week":0,"raw_downloads_day":0,"tags":["407a57f66de7fe3d7c4dc8631b90adba5d1540e0","pr-4800"]},{"id":957234208,"name":"sha256:3767bee35ac8583f0d64c6b11d540499d6ed845883fb8f4767db9b3fd53ef01a","date":"2026-06-22","newest":false,"latest":false,"size":"269.4 MB","downloads":"5","downloads_month":"5","downloads_week":"5","downloads_day":"0","raw_size":269468227,"raw_downloads":5,"raw_downloads_month":5,"raw_downloads_week":5,"raw_downloads_day":0,"tags":["05ff3329a26e4012e12c71bad5299caa27d6f41a"]},{"id":957237024,"name":"sha256:cb6c6f83bf80953b7adb72ef026d7ed3898b17a2bacb688a5638f866d69c8c66","date":"2026-06-22","newest":false,"latest":false,"size":"269.4 MB","downloads":"0","downloads_month":"0","downloads_week":"0","downloads_day":"0","raw_size":269456900,"raw_downloads":0,"raw_downloads_month":0,"raw_downloads_week":0,"raw_downloads_day":0,"tags":["f96a3340799a29b091629ec191ce9810349c19e3","pr-4821"]},{"id":957508306,"name":"sha256:6c60c250ddc24c56e48bf68bf2a1630d4468ecc6aaa68282ee4303c125de29ce","date":"2026-06-22","newest":false,"latest":false,"size":"269.4 MB","downloads":"29","downloads_month":"29","downloads_week":"29","downloads_day":"0","raw_size":269460852,"raw_downloads":29,"raw_downloads_month":29,"raw_downloads_week":29,"raw_downloads_day":0,"tags":["8e81b5d1ad67054b42ddfe8b4b802d3b57e8958e"]},{"id":959087284,"name":"sha256:4ebcb0b3384a20e1ae8e700fad67fec55c7ac498a89d156330ae0c5a58d078d0","date":"2026-06-22","newest":false,"latest":false,"size":"269.4 MB","downloads":"0","downloads_month":"0","downloads_week":"0","downloads_day":"0","raw_size":269484080,"raw_downloads":0,"raw_downloads_month":0,"raw_downloads_week":0,"raw_downloads_day":0,"tags":["1e54ff9ac5cd8f4d1d4eb85bdfcdd6518c9a2e8a","pr-4816"]},{"id":959092958,"name":"sha256:4005dbf00562a39303916a9aadd6b747de45c21e59c396f0d5fe3beb1a207bb1","date":"2026-06-22","newest":false,"latest":false,"size":"269.4 MB","downloads":"5","downloads_month":"5","downloads_week":"5","downloads_day":"0","raw_size":269479424,"raw_downloads":5,"raw_downloads_month":5,"raw_downloads_week":5,"raw_downloads_day":0,"tags":["ca0bd62358e9cfcd44d79f1c4e7d77399a635126"]},{"id":959125931,"name":"sha256:9742782855ed0549f9c4e06e19b68c73b8f6abcf822832b8bd0a8542b88fafd8","date":"2026-06-22","newest":false,"latest":false,"size":"269.4 MB","downloads":"32","downloads_month":"32","downloads_week":"32","downloads_day":"0","raw_size":269459103,"raw_downloads":32,"raw_downloads_month":32,"raw_downloads_week":32,"raw_downloads_day":0,"tags":["0ae4fc4fe2a417b901dae656d8a38c37f0cc0797"]},{"id":959129236,"name":"sha256:0772323b41afb539f6d0bec9279cacf228b29871e6e407b46950ff60b5b810c4","date":"2026-06-22","newest":false,"latest":false,"size":"269.4 MB","downloads":"5","downloads_month":"5","downloads_week":"5","downloads_day":"0","raw_size":269452137,"raw_downloads":5,"raw_downloads_month":5,"raw_downloads_week":5,"raw_downloads_day":0,"tags":["1b80d11e5ce47857750ea40dded07d5eb03d0d24","pr-4811"]},{"id":959144812,"name":"sha256:6f403eb2ca99974b83d76ffcb2798ecf8709d440243c279992a77d8a4f64342a","date":"2026-06-22","newest":false,"latest":false,"size":"269.4 MB","downloads":"5","downloads_month":"5","downloads_week":"5","downloads_day":"0","raw_size":269455782,"raw_downloads":5,"raw_downloads_month":5,"raw_downloads_week":5,"raw_downloads_day":0,"tags":["d0b5c5349808ad6e71ad0c3eed33d9ae1dd8f8eb"]},{"id":959174987,"name":"sha256:0fd805eacbd6acd97026dcd62b65dc0c64c9eeb4178da019988e1b373a47073b","date":"2026-06-22","newest":false,"latest":false,"size":"269.4 MB","downloads":"5","downloads_month":"5","downloads_week":"5","downloads_day":"0","raw_size":269458025,"raw_downloads":5,"raw_downloads_month":5,"raw_downloads_week":5,"raw_downloads_day":0,"tags":["ca33371114fbc3804dfc51fe424fe3879f56f8cb"]},{"id":959178628,"name":"sha256:5fc3492cbbc1951664a07e8a01dbff4bb18321c5d61b1d2f500ab66822db5366","date":"2026-06-22","newest":false,"latest":false,"size":"269.4 MB","downloads":"5","downloads_month":"5","downloads_week":"5","downloads_day":"0","raw_size":269455783,"raw_downloads":5,"raw_downloads_month":5,"raw_downloads_week":5,"raw_downloads_day":0,"tags":["a3fdac17354a5d5b951ed5c5e8f559a0c8f86c0e","pr-4824"]},{"id":959194919,"name":"sha256:ed79bad585fd6de3e755b22d7ae2dafc42339f67864fb1d7ebfb6ec35945934a","date":"2026-06-22","newest":false,"latest":false,"size":"269.4 MB","downloads":"0","downloads_month":"0","downloads_week":"0","downloads_day":"0","raw_size":269455415,"raw_downloads":0,"raw_downloads_month":0,"raw_downloads_week":0,"raw_downloads_day":0,"tags":["e219d3c27a84df922e53bc37e61abbad6bb253e3"]},{"id":959213837,"name":"sha256:54953d9f30a544844c220ab03304d75a429446af92d401d605bc3f2a20f611b4","date":"2026-06-22","newest":false,"latest":false,"size":"269.4 MB","downloads":"5","downloads_month":"5","downloads_week":"5","downloads_day":"0","raw_size":269458537,"raw_downloads":5,"raw_downloads_month":5,"raw_downloads_week":5,"raw_downloads_day":0,"tags":["77b4d4a595e4be465e2d067f488fadb687da56bd"]},{"id":959218741,"name":"sha256:7eb4e2320ac3c1eba51109370adbb5dccfbb5726571ac08610934d7887a366cf","date":"2026-06-22","newest":false,"latest":false,"size":"269.4 MB","downloads":"0","downloads_month":"0","downloads_week":"0","downloads_day":"0","raw_size":269475142,"raw_downloads":0,"raw_downloads_month":0,"raw_downloads_week":0,"raw_downloads_day":0,"tags":["ab5060d5d0bba4670ac4181e87453b79e4dbd23c","pr-4823"]},{"id":959243156,"name":"sha256:4874fa70b331304d7653bd4cbf151f718d6a90d24a2b994fcab36d73c158c406","date":"2026-06-22","newest":false,"latest":false,"size":"269.4 MB","downloads":"5","downloads_month":"5","downloads_week":"5","downloads_day":"0","raw_size":269472927,"raw_downloads":5,"raw_downloads_month":5,"raw_downloads_week":5,"raw_downloads_day":0,"tags":["ba3df6d05fc2d1fc9f9b626717714d39fd7f97e2"]},{"id":959248679,"name":"sha256:984c33f73ad2ff31ed46b73fa478e3b74b996bd74a190ba6a10c4e4542e99af3","date":"2026-06-22","newest":false,"latest":false,"size":"269.4 MB","downloads":"5","downloads_month":"5","downloads_week":"5","downloads_day":"0","raw_size":269458434,"raw_downloads":5,"raw_downloads_month":5,"raw_downloads_week":5,"raw_downloads_day":0,"tags":["6f464da00f1fa8a384367e71b44272f3535a3074"]},{"id":959270237,"name":"sha256:1332f6f1bcc5edafa802abe24111a34c9b5a3656d40bddb75b76b96eeda8a12b","date":"2026-06-22","newest":false,"latest":false,"size":"269.4 MB","downloads":"0","downloads_month":"0","downloads_week":"0","downloads_day":"0","raw_size":269455415,"raw_downloads":0,"raw_downloads_month":0,"raw_downloads_week":0,"raw_downloads_day":0,"tags":["2a2293bc33c16e190247c3da2659c1756d5cbb06","pr-4818"]},{"id":959272393,"name":"sha256:e461313669632600d5a8eab8a75ed6127856a79e89d4597aada1bfbde21b08a0","date":"2026-06-22","newest":false,"latest":false,"size":"269.4 MB","downloads":"0","downloads_month":"0","downloads_week":"0","downloads_day":"0","raw_size":269474989,"raw_downloads":0,"raw_downloads_month":0,"raw_downloads_week":0,"raw_downloads_day":0,"tags":["0491cf3e501aca8253e9319ac9137649a42e5217","pr-4790"]},{"id":959280371,"name":"sha256:a27d75ea5653db2248aef38cb86c5c527b186b3616701aedafebcb6eebc3a6da","date":"2026-06-22","newest":false,"latest":false,"size":"269.4 MB","downloads":"5","downloads_month":"5","downloads_week":"5","downloads_day":"0","raw_size":269473141,"raw_downloads":5,"raw_downloads_month":5,"raw_downloads_week":5,"raw_downloads_day":0,"tags":["591f6e2a650f32071f53d626bf3f95f60578230e"]},{"id":959325159,"name":"sha256:bf17af5c6e956ee37f285ac858ef87ae60a72c4566bc4ddf3d521ee33950fbcc","date":"2026-06-22","newest":false,"latest":false,"size":"269.4 MB","downloads":"19","downloads_month":"19","downloads_week":"19","downloads_day":"0","raw_size":269437060,"raw_downloads":19,"raw_downloads_month":19,"raw_downloads_week":19,"raw_downloads_day":0,"tags":["09514225f45373d8701f0323f78eafdcea244421"]},{"id":959329470,"name":"sha256:2a028dfa672d85149d8385f2d697042094188aa4d438aa4430b5bd22c8e92f74","date":"2026-06-22","newest":false,"latest":false,"size":"269.4 MB","downloads":"5","downloads_month":"5","downloads_week":"5","downloads_day":"0","raw_size":269480235,"raw_downloads":5,"raw_downloads_month":5,"raw_downloads_week":5,"raw_downloads_day":0,"tags":["188125831611f5be141b9f0a2822a2f539172b8a"]},{"id":959363803,"name":"sha256:06dbfde47a1a06ba6caa38284f8f85a615e8d1e87e49e173060900e93014c0b0","date":"2026-06-22","newest":false,"latest":false,"size":"269.4 MB","downloads":"0","downloads_month":"0","downloads_week":"0","downloads_day":"0","raw_size":269481946,"raw_downloads":0,"raw_downloads_month":0,"raw_downloads_week":0,"raw_downloads_day":0,"tags":["20a928021dfd26e8ec42d0fcaa9b45f29e338b0c","pr-4820"]},{"id":959380296,"name":"sha256:ff89154e2590a7d48e465823d57706854b44ac178302ad0cc264a0e0a525ef69","date":"2026-06-22","newest":false,"latest":false,"size":"269.4 MB","downloads":"5","downloads_month":"5","downloads_week":"5","downloads_day":"0","raw_size":269454367,"raw_downloads":5,"raw_downloads_month":5,"raw_downloads_week":5,"raw_downloads_day":0,"tags":["643565141f1dc80ea35f5ade001a2013f5ac5ff3","pr-4783"]},{"id":959386130,"name":"sha256:4c283f0d1659d67f09720ed5da3d2925da1c3584fd179c9c74d1e24650090f99","date":"2026-06-22","newest":false,"latest":false,"size":"269.4 MB","downloads":"799","downloads_month":"799","downloads_week":"799","downloads_day":"115","raw_size":269436581,"raw_downloads":799,"raw_downloads_month":799,"raw_downloads_week":799,"raw_downloads_day":115,"tags":["3f2d52139c7c35ee5396e100db388e9b5ac2047d"]},{"id":959388017,"name":"sha256:df9661d75745a7408c3260602f3e74adba224bb25a853a7f5ede400fe119e50f","date":"2026-06-22","newest":false,"latest":false,"size":"269.4 MB","downloads":"5","downloads_month":"5","downloads_week":"5","downloads_day":"0","raw_size":269453827,"raw_downloads":5,"raw_downloads_month":5,"raw_downloads_week":5,"raw_downloads_day":0,"tags":["ddd8803d543b3eb7c1d2ba33bbec248837911f75","pr-4817"]},{"id":959419197,"name":"sha256:61f82817b1ecd459cf6d5ac188fdec6289dbbb08f4d00fcf30dd583e646d9a35","date":"2026-06-22","newest":false,"latest":false,"size":"269.4 MB","downloads":"5","downloads_month":"5","downloads_week":"5","downloads_day":"0","raw_size":269437504,"raw_downloads":5,"raw_downloads_month":5,"raw_downloads_week":5,"raw_downloads_day":0,"tags":["6988cdb26d2225aa1400758ca248dd7bc3c022c3"]},{"id":959445349,"name":"sha256:ea65cba6077027eecd2721a5d8fe982b5f45437cf94e7d44deff8004fbbb5783","date":"2026-06-22","newest":false,"latest":false,"size":"269.4 MB","downloads":"5","downloads_month":"5","downloads_week":"5","downloads_day":"0","raw_size":269479672,"raw_downloads":5,"raw_downloads_month":5,"raw_downloads_week":5,"raw_downloads_day":0,"tags":["39150e815f77e5e10cb35c78ea585dcfbf7e81c5","pr-4829"]},{"id":959827223,"name":"sha256:34c3acdd26ab4f4f500c160f9a5731c9a01a4b23c08bb9c2e0a5c7ce5aa7339f","date":"2026-06-22","newest":false,"latest":false,"size":"269.4 MB","downloads":"5","downloads_month":"5","downloads_week":"5","downloads_day":"0","raw_size":269454741,"raw_downloads":5,"raw_downloads_month":5,"raw_downloads_week":5,"raw_downloads_day":0,"tags":["1ed137b0cdaaecaa494ab7cb4f8347c8f1a99ddd","pr-4777"]},{"id":959863308,"name":"sha256:c149e8cacccf2c7794c7a028876ef8df164eedaa2604633c437f2eac6dbcddc8","date":"2026-06-22","newest":false,"latest":false,"size":"269.4 MB","downloads":"0","downloads_month":"0","downloads_week":"0","downloads_day":"0","raw_size":269453296,"raw_downloads":0,"raw_downloads_month":0,"raw_downloads_week":0,"raw_downloads_day":0,"tags":["e2ea716e2c1e9d1e9124b9f13bb12f476a0409bd"]},{"id":959879479,"name":"sha256:e7e1d3a47f072c79b7c9174d12010a0fef69af177038275b6d5601fe1f8265bf","date":"2026-06-22","newest":false,"latest":false,"size":"269.4 MB","downloads":"0","downloads_month":"0","downloads_week":"0","downloads_day":"0","raw_size":269453482,"raw_downloads":0,"raw_downloads_month":0,"raw_downloads_week":0,"raw_downloads_day":0,"tags":["ae4ea923c9394e45fe3d2aa1afe632d080b64142"]},{"id":959904648,"name":"sha256:c85c7680a088885f105fd091ad6ff4ccae3e3fc1777c3305bd96e374497add3f","date":"2026-06-22","newest":false,"latest":false,"size":"269.4 MB","downloads":"0","downloads_month":"0","downloads_week":"0","downloads_day":"0","raw_size":269453088,"raw_downloads":0,"raw_downloads_month":0,"raw_downloads_week":0,"raw_downloads_day":0,"tags":["06aeeaad4ad7c0797cee78273b187c5b8a4d6914","pr-4831"]},{"id":959917421,"name":"sha256:0c61c9fb81ef44b5a0ce39621386a8b83d6cb04a244520ced8e98e275cd2e53c","date":"2026-06-22","newest":false,"latest":false,"size":"269.4 MB","downloads":"0","downloads_month":"0","downloads_week":"0","downloads_day":"0","raw_size":269453628,"raw_downloads":0,"raw_downloads_month":0,"raw_downloads_week":0,"raw_downloads_day":0,"tags":["f68c52ff9a876515d9131ecf5efbbe2e06450582","pr-4832"]},{"id":959943088,"name":"sha256:9cbd5f49ec0c2bbb498f8a1336610aaba746b52569c09d01081dfbb340ccdd82","date":"2026-06-22","newest":false,"latest":false,"size":"269.4 MB","downloads":"5","downloads_month":"5","downloads_week":"5","downloads_day":"0","raw_size":269457315,"raw_downloads":5,"raw_downloads_month":5,"raw_downloads_week":5,"raw_downloads_day":0,"tags":["22996dc454fab65593cc75a77a3fee5e90ee0435","pr-4813"]},{"id":959945016,"name":"sha256:746f80204cc83d6daec8c4a749ab76bc17b56046d5048fab2972180b4a69da77","date":"2026-06-22","newest":false,"latest":false,"size":"269.4 MB","downloads":"0","downloads_month":"0","downloads_week":"0","downloads_day":"0","raw_size":269497627,"raw_downloads":0,"raw_downloads_month":0,"raw_downloads_week":0,"raw_downloads_day":0,"tags":["50aabb10bc63302fac978d7827f6aeff6906724a"]},{"id":959973073,"name":"sha256:f28bf8f988ba07085f4e9832a26a9c111781b0c4182d94719117339ed809d161","date":"2026-06-22","newest":false,"latest":false,"size":"269.4 MB","downloads":"5","downloads_month":"5","downloads_week":"5","downloads_day":"0","raw_size":269437579,"raw_downloads":5,"raw_downloads_month":5,"raw_downloads_week":5,"raw_downloads_day":0,"tags":["97309953e116fde07a125ca9bb1ea5d3bc14394c"]},{"id":959973821,"name":"sha256:80f8f528b6913b013cfc8d283a8cd71874ec35ed645c79336b2e84c136547c54","date":"2026-06-22","newest":false,"latest":false,"size":"269.4 MB","downloads":"0","downloads_month":"0","downloads_week":"0","downloads_day":"0","raw_size":269472868,"raw_downloads":0,"raw_downloads_month":0,"raw_downloads_week":0,"raw_downloads_day":0,"tags":["8324548430ffd39f6f05d0ae00ac0ca84b6d9405","pr-4796"]},{"id":960483201,"name":"sha256:b5242fa85a459c75d61ca0d3cab6b8b223563bbb5691d8a67527b7f40c8bf3ad","date":"2026-06-22","newest":false,"latest":false,"size":"284.9 MB","downloads":"5","downloads_month":"5","downloads_week":"5","downloads_day":"0","raw_size":284931876,"raw_downloads":5,"raw_downloads_month":5,"raw_downloads_week":5,"raw_downloads_day":0,"tags":["7bd7d8f24eed3334cb24e2214c7b89a67f3b47ce","pr-4834"]},{"id":963518485,"name":"sha256:8bb3abbe01a66c916bd1d09b16fb8850bfd98b3b63e69ae18e06398278530635","date":"2026-06-22","newest":false,"latest":false,"size":"269.4 MB","downloads":"7","downloads_month":"7","downloads_week":"7","downloads_day":"7","raw_size":269471515,"raw_downloads":7,"raw_downloads_month":7,"raw_downloads_week":7,"raw_downloads_day":7,"tags":["40476d72df22106b6bda236f19b30d15affcc68f","nightly"]},{"id":964195868,"name":"sha256:423b547da689f1eace04b74172691d9ff26a1f46f171c522fd9c016d1d0be512","date":"2026-06-22","newest":false,"latest":false,"size":"96.4 kB","downloads":"0","downloads_month":"0","downloads_week":"0","downloads_day":"0","raw_size":96495,"raw_downloads":0,"raw_downloads_month":0,"raw_downloads_week":0,"raw_downloads_day":0,"tags":[]},{"id":964195897,"name":"sha256:97f2a098b5c01c765cf8a55a53378c315e573d7c77b150d7dc549c6ed4fd8dbe","date":"2026-06-22","newest":false,"latest":false,"size":"269.5 MB","downloads":"5","downloads_month":"5","downloads_week":"5","downloads_day":"5","raw_size":269531980,"raw_downloads":5,"raw_downloads_month":5,"raw_downloads_week":5,"raw_downloads_day":5,"tags":["be40bcd399f2ae049f4e5d9426801266d84ad805","pr-4836"]},{"id":964196515,"name":"sha256:2e9e04daa07a0a524be84b1a18537873c23fec3003f6f1efa336785e128b736b","date":"2026-06-22","newest":false,"latest":false,"size":"269.4 MB","downloads":"5","downloads_month":"5","downloads_week":"5","downloads_day":"5","raw_size":269441737,"raw_downloads":5,"raw_downloads_month":5,"raw_downloads_week":5,"raw_downloads_day":5,"tags":[]},{"id":964196554,"name":"sha256:e19099b89ad86cc68774fdf3500d9b314498a1e6aa4ff0780815d41fa0941310","date":"2026-06-22","newest":false,"latest":false,"size":"64.4 kB","downloads":"0","downloads_month":"0","downloads_week":"0","downloads_day":"0","raw_size":64428,"raw_downloads":0,"raw_downloads_month":0,"raw_downloads_week":0,"raw_downloads_day":0,"tags":[]},{"id":964196594,"name":"sha256:e986acf7dcc6cbd5b59aa5d885ff8ed4f2f3c34b59ce9949edf3ae8fa0da917e","date":"2026-06-22","newest":true,"latest":true,"size":"269.4 MB","downloads":"5","downloads_month":"5","downloads_week":"5","downloads_day":"5","raw_size":269499913,"raw_downloads":5,"raw_downloads_month":5,"raw_downloads_week":5,"raw_downloads_day":5,"tags":["b1c0b6d7180aacb3b9414b7de8f589bfe3be362d","pr-4837","latest"]}]}
