{"owner_type":"users","package_type":"container","owner_id":10111,"owner":"mattn","repo":"multi-server","package":"multi-server","date":"2026-02-05","size":"2.4 MB","versions":"20","tagged":"7","owner_rank":"40","repo_rank":"1","downloads":"75","downloads_month":"14","downloads_week":"12","downloads_day":"12","raw_size":2422210,"raw_versions":20,"raw_tagged":7,"raw_owner_rank":40,"raw_repo_rank":1,"raw_downloads":75,"raw_downloads_month":14,"raw_downloads_week":12,"raw_downloads_day":12,"version":[{"id":560319584,"name":"sha256:95f05875400c4d01c2761ad711dbb4312413c512c9f5f56d09e32a3c154df58c","date":"2026-02-05","newest":false,"latest":false,"size":"2.6 kB","downloads":"0","downloads_month":"0","downloads_week":"0","downloads_day":"0","raw_size":2614,"raw_downloads":0,"raw_downloads_month":0,"raw_downloads_week":0,"raw_downloads_day":0,"tags":[]},{"id":560319588,"name":"sha256:b02102c6a9e84f1719231c9b72973b11538852b9b22c28b4838401d2b47324bc","date":"2026-02-05","newest":false,"latest":false,"size":"2.4 MB","downloads":"1","downloads_month":"0","downloads_week":"0","downloads_day":"0","raw_size":2422210,"raw_downloads":1,"raw_downloads_month":0,"raw_downloads_week":0,"raw_downloads_day":0,"tags":["v0.0.1"]},{"id":560393822,"name":"sha256:ef0d93d2aec532917264849db0751573012ab718c5a531d7dbe7fb0d70eec4ce","date":"2026-02-05","newest":false,"latest":false,"size":"2.4 MB","downloads":"4","downloads_month":"0","downloads_week":"0","downloads_day":"0","raw_size":2428691,"raw_downloads":4,"raw_downloads_month":0,"raw_downloads_week":0,"raw_downloads_day":0,"tags":[]},{"id":560393844,"name":"sha256:7d8e43ebbacf80d1865d6a3eeb487e44a88d580efb364c9698124eda68dade74","date":"2026-02-05","newest":false,"latest":false,"size":"2.6 kB","downloads":"0","downloads_month":"0","downloads_week":"0","downloads_day":"0","raw_size":2615,"raw_downloads":0,"raw_downloads_month":0,"raw_downloads_week":0,"raw_downloads_day":0,"tags":[]},{"id":560393875,"name":"sha256:53d56999d1545eb01048369a0ed4782c5421e43be63ef2c7d6fc6d34ccd058c1","date":"2026-02-05","newest":false,"latest":false,"size":"2.4 MB","downloads":"4","downloads_month":"0","downloads_week":"0","downloads_day":"0","raw_size":2422210,"raw_downloads":4,"raw_downloads_month":0,"raw_downloads_week":0,"raw_downloads_day":0,"tags":["v0.0.2"]},{"id":560450914,"name":"sha256:d115df0ce8e6c9d41c06bd70c79fecb10698235dddbd9b33262f76a6f71291a8","date":"2026-02-05","newest":false,"latest":false,"size":"2.4 MB","downloads":"14","downloads_month":"0","downloads_week":"0","downloads_day":"0","raw_size":2428679,"raw_downloads":14,"raw_downloads_month":0,"raw_downloads_week":0,"raw_downloads_day":0,"tags":[]},{"id":560450920,"name":"sha256:7166c473cbeeb62b2fa4a6117229020ae8bc362bc47ea69368ac9fbb1d20bf75","date":"2026-02-05","newest":false,"latest":false,"size":"2.6 kB","downloads":"0","downloads_month":"0","downloads_week":"0","downloads_day":"0","raw_size":2615,"raw_downloads":0,"raw_downloads_month":0,"raw_downloads_week":0,"raw_downloads_day":0,"tags":[]},{"id":560450924,"name":"sha256:77fc5729b896829e96b1c7c89b98eff0e0e601b7201632bf530232126dfb29d0","date":"2026-02-05","newest":false,"latest":false,"size":"2.4 MB","downloads":"14","downloads_month":"0","downloads_week":"0","downloads_day":"0","raw_size":2422210,"raw_downloads":14,"raw_downloads_month":0,"raw_downloads_week":0,"raw_downloads_day":0,"tags":["v0.0.3"]},{"id":562816786,"name":"sha256:4e1f62240732629c47784f8d444c552012591c44671b74738f5b9ec54d8f8b37","date":"2026-02-05","newest":false,"latest":false,"size":"2.4 MB","downloads":"5","downloads_month":"0","downloads_week":"0","downloads_day":"0","raw_size":2428950,"raw_downloads":5,"raw_downloads_month":0,"raw_downloads_week":0,"raw_downloads_day":0,"tags":[]},{"id":562816788,"name":"sha256:e7a140f0e74750c08eb1f1571e92bce49e00a4d65e72830e93ee8dfa5ae07075","date":"2026-02-05","newest":false,"latest":false,"size":"2.6 kB","downloads":"0","downloads_month":"0","downloads_week":"0","downloads_day":"0","raw_size":2613,"raw_downloads":0,"raw_downloads_month":0,"raw_downloads_week":0,"raw_downloads_day":0,"tags":[]},{"id":562816791,"name":"sha256:2c356b5373fd588e3f04b2d67301faed7a6602fbb0b479c42f647151d65fc3d6","date":"2026-02-05","newest":false,"latest":false,"size":"2.4 MB","downloads":"5","downloads_month":"0","downloads_week":"0","downloads_day":"0","raw_size":2422210,"raw_downloads":5,"raw_downloads_month":0,"raw_downloads_week":0,"raw_downloads_day":0,"tags":["v0.0.4"]},{"id":562921351,"name":"sha256:95aeb8699ba9883e591dee0cd143e536ae6655a29fd2a249904e41b7d69af33c","date":"2026-02-05","newest":false,"latest":false,"size":"2.4 MB","downloads":"2","downloads_month":"0","downloads_week":"0","downloads_day":"0","raw_size":2429063,"raw_downloads":2,"raw_downloads_month":0,"raw_downloads_week":0,"raw_downloads_day":0,"tags":[]},{"id":562921352,"name":"sha256:e934d29f26bd7df04147092a5c6bb7fe63475b938eb9de2b363af72f3f055b07","date":"2026-02-05","newest":false,"latest":false,"size":"2.6 kB","downloads":"0","downloads_month":"0","downloads_week":"0","downloads_day":"0","raw_size":2615,"raw_downloads":0,"raw_downloads_month":0,"raw_downloads_week":0,"raw_downloads_day":0,"tags":[]},{"id":562921354,"name":"sha256:1ea2537c40d02826172992d5c86da9421ca1e23c4baebc4e5b3b54710d195076","date":"2026-02-05","newest":false,"latest":false,"size":"2.4 MB","downloads":"2","downloads_month":"0","downloads_week":"0","downloads_day":"0","raw_size":2422210,"raw_downloads":2,"raw_downloads_month":0,"raw_downloads_week":0,"raw_downloads_day":0,"tags":["v0.0.5"]},{"id":562934071,"name":"sha256:c7744bc629aeeda8eeb9bdf8a3ee1c811000ecedc926a57cbe4123e2767f96f6","date":"2026-02-05","newest":false,"latest":false,"size":"2.4 MB","downloads":"2","downloads_month":"0","downloads_week":"0","downloads_day":"0","raw_size":2428959,"raw_downloads":2,"raw_downloads_month":0,"raw_downloads_week":0,"raw_downloads_day":0,"tags":[]},{"id":562934073,"name":"sha256:fdd877803e7508834ee1387b05bb3012c0186a6868554dd1cf574622991e533f","date":"2026-02-05","newest":false,"latest":false,"size":"2.6 kB","downloads":"0","downloads_month":"0","downloads_week":"0","downloads_day":"0","raw_size":2615,"raw_downloads":0,"raw_downloads_month":0,"raw_downloads_week":0,"raw_downloads_day":0,"tags":[]},{"id":562934074,"name":"sha256:2fa949cd8726f460e0ccfd102229eab23b759b053cd1e1b9de5922e517fd41b6","date":"2026-02-05","newest":false,"latest":false,"size":"2.4 MB","downloads":"4","downloads_month":"0","downloads_week":"0","downloads_day":"0","raw_size":2422210,"raw_downloads":4,"raw_downloads_month":0,"raw_downloads_week":0,"raw_downloads_day":0,"tags":["v0.0.6"]},{"id":571699818,"name":"sha256:dd2ac039a9bdf04d12b9bf805a6054030daad88f36acb4930d06eefeb3eb243a","date":"2026-02-05","newest":false,"latest":false,"size":"2.4 MB","downloads":"9","downloads_month":"7","downloads_week":"6","downloads_day":"6","raw_size":2429244,"raw_downloads":9,"raw_downloads_month":7,"raw_downloads_week":6,"raw_downloads_day":6,"tags":[]},{"id":571699829,"name":"sha256:73ef2ebecf71a0a3c22d27f61cadbfd4d7db41f6ecd2c97a1dd04c53d4add6fb","date":"2026-02-05","newest":false,"latest":false,"size":"2.6 kB","downloads":"0","downloads_month":"0","downloads_week":"0","downloads_day":"0","raw_size":2615,"raw_downloads":0,"raw_downloads_month":0,"raw_downloads_week":0,"raw_downloads_day":0,"tags":[]},{"id":571699840,"name":"sha256:3cfd96bf180b68e2327276bb6eef2a9542bd404c77b417662e1544e4822fcf7a","date":"2026-02-05","newest":true,"latest":true,"size":"2.4 MB","downloads":"9","downloads_month":"7","downloads_week":"6","downloads_day":"6","raw_size":2422210,"raw_downloads":9,"raw_downloads_month":7,"raw_downloads_week":6,"raw_downloads_day":6,"tags":["v0.0.7","latest"]}]}
