<?xml version="1.0" encoding="UTF-8"?><xml><owner_type>orgs</owner_type><package_type>container</package_type><owner_id>93954236</owner_id><owner>cross-rs</owner><repo>cross</repo><package>x86_64-unknown-illumos</package><date>2026-04-23</date><size>17.2 kB</size><versions>33</versions><tagged>4</tagged><owner_rank>26</owner_rank><repo_rank>26</repo_rank><downloads>79.2k</downloads><downloads_month>2.5k</downloads_month><downloads_week>626</downloads_week><downloads_day>47</downloads_day><raw_size>17288</raw_size><raw_versions>33</raw_versions><raw_tagged>4</raw_tagged><raw_owner_rank>26</raw_owner_rank><raw_repo_rank>26</raw_repo_rank><raw_downloads>79245</raw_downloads><raw_downloads_month>2524</raw_downloads_month><raw_downloads_week>626</raw_downloads_week><raw_downloads_day>47</raw_downloads_day><version><id>28032609</id><name>sha256:256628f3f9e755d628b821d88ca2718b3afa01fc95e7879e83d0baef08cab686</name><date>2026-04-23</date><newest>false</newest><latest>false</latest><size>450.7 MB</size><downloads>177</downloads><downloads_month>15</downloads_month><downloads_week>8</downloads_week><downloads_day>1</downloads_day><raw_size>450719444</raw_size><raw_downloads>177</raw_downloads><raw_downloads_month>15</raw_downloads_month><raw_downloads_week>8</raw_downloads_week><raw_downloads_day>1</raw_downloads_day><tags>0.2.3</tags></version><version><id>28076660</id><name>sha256:b6b7ab650e1a8273187a4ce1b024cd32c4b33d8ddc61f8aba9df621823576c39</name><date>2026-04-23</date><newest>false</newest><latest>false</latest><size>450.7 MB</size><downloads>3.2k</downloads><downloads_month>15</downloads_month><downloads_week>8</downloads_week><downloads_day>1</downloads_day><raw_size>450719444</raw_size><raw_downloads>3203</raw_downloads><raw_downloads_month>15</raw_downloads_month><raw_downloads_week>8</raw_downloads_week><raw_downloads_day>1</raw_downloads_day><tags>0.2.4</tags></version><version><id>68147930</id><name>sha256:206f71ec47b79bfff85f7f28162bcdb01eb42dcc7e0a3c00bd10569fe12de823</name><date>2026-04-23</date><newest>false</newest><latest>true</latest><size>-1</size><downloads>28.2k</downloads><downloads_month>1.2k</downloads_month><downloads_week>286</downloads_week><downloads_day>13</downloads_day><raw_size>-1</raw_size><raw_downloads>28235</raw_downloads><raw_downloads_month>1260</raw_downloads_month><raw_downloads_week>286</raw_downloads_week><raw_downloads_day>13</raw_downloads_day><tags>latest</tags><tags>0.2.5</tags></version><version><id>708041343</id><name>sha256:36d109d00b0126ff5e1e69d16e28da4fdd086acd86193397eef7f27abb7bcc1a</name><date>2026-04-23</date><newest>false</newest><latest>false</latest><size>515.8 MB</size><downloads>171</downloads><downloads_month>0</downloads_month><downloads_week>0</downloads_week><downloads_day>0</downloads_day><raw_size>515836866</raw_size><raw_downloads>171</raw_downloads><raw_downloads_month>0</raw_downloads_month><raw_downloads_week>0</raw_downloads_week><raw_downloads_day>0</raw_downloads_day></version><version><id>708041351</id><name>sha256:c481bb3d6061220f749bba3a664e7ab51b895e3a57dc453cc7fd643dbce1bbe6</name><date>2026-04-23</date><newest>false</newest><latest>false</latest><size>9.1 kB</size><downloads>2</downloads><downloads_month>0</downloads_month><downloads_week>0</downloads_week><downloads_day>0</downloads_day><raw_size>9160</raw_size><raw_downloads>2</raw_downloads><raw_downloads_month>0</raw_downloads_month><raw_downloads_week>0</raw_downloads_week><raw_downloads_day>0</raw_downloads_day></version><version><id>708041357</id><name>sha256:8601b312d0593b71f0d09eeee3c2a973f1e913909f9edf222ef51f92001d4aee</name><date>2026-04-23</date><newest>false</newest><latest>false</latest><size>-1</size><downloads>171</downloads><downloads_month>0</downloads_month><downloads_week>0</downloads_week><downloads_day>0</downloads_day><raw_size>-1</raw_size><raw_downloads>171</raw_downloads><raw_downloads_month>0</raw_downloads_month><raw_downloads_week>0</raw_downloads_week><raw_downloads_day>0</raw_downloads_day></version><version><id>720449031</id><name>sha256:d35bfec8ca2e7b448302bb626c7174786f379017f8add3f7729874b54004ad42</name><date>2026-04-23</date><newest>false</newest><latest>false</latest><size>515.8 MB</size><downloads>136</downloads><downloads_month>0</downloads_month><downloads_week>0</downloads_week><downloads_day>0</downloads_day><raw_size>515836866</raw_size><raw_downloads>136</raw_downloads><raw_downloads_month>0</raw_downloads_month><raw_downloads_week>0</raw_downloads_week><raw_downloads_day>0</raw_downloads_day></version><version><id>720449037</id><name>sha256:ce1cd18ded8468cabd13c6fe9a7b8bd7ab7d3233b7e04bab43f561b91d76ba52</name><date>2026-04-23</date><newest>false</newest><latest>false</latest><size>9.1 kB</size><downloads>3</downloads><downloads_month>0</downloads_month><downloads_week>0</downloads_week><downloads_day>0</downloads_day><raw_size>9161</raw_size><raw_downloads>3</raw_downloads><raw_downloads_month>0</raw_downloads_month><raw_downloads_week>0</raw_downloads_week><raw_downloads_day>0</raw_downloads_day></version><version><id>720449041</id><name>sha256:3fa5c20fe234faca40bf0e0626e09d02c982c2336c66ecaf78041d30f083ffef</name><date>2026-04-23</date><newest>false</newest><latest>false</latest><size>-1</size><downloads>138</downloads><downloads_month>0</downloads_month><downloads_week>0</downloads_week><downloads_day>0</downloads_day><raw_size>-1</raw_size><raw_downloads>138</raw_downloads><raw_downloads_month>0</raw_downloads_month><raw_downloads_week>0</raw_downloads_week><raw_downloads_day>0</raw_downloads_day></version><version><id>733498025</id><name>sha256:9c25a66d23b1586d2f3d757229f734f4942095f132eeeb073912ec5598c39c24</name><date>2026-04-23</date><newest>false</newest><latest>false</latest><size>515.8 MB</size><downloads>128</downloads><downloads_month>0</downloads_month><downloads_week>0</downloads_week><downloads_day>0</downloads_day><raw_size>515836866</raw_size><raw_downloads>128</raw_downloads><raw_downloads_month>0</raw_downloads_month><raw_downloads_week>0</raw_downloads_week><raw_downloads_day>0</raw_downloads_day></version><version><id>733498033</id><name>sha256:56e4ac444fa02b23bcf19f318e2e95be3472d6ba3e6bf2c83406f20f4deabbe8</name><date>2026-04-23</date><newest>false</newest><latest>false</latest><size>9.1 kB</size><downloads>4</downloads><downloads_month>0</downloads_month><downloads_week>0</downloads_week><downloads_day>0</downloads_day><raw_size>9160</raw_size><raw_downloads>4</raw_downloads><raw_downloads_month>0</raw_downloads_month><raw_downloads_week>0</raw_downloads_week><raw_downloads_day>0</raw_downloads_day></version><version><id>733498040</id><name>sha256:c771ab17c671da50298609025b4d1bebd743a138b9d700a228a876636028cbf5</name><date>2026-04-23</date><newest>false</newest><latest>false</latest><size>-1</size><downloads>136</downloads><downloads_month>0</downloads_month><downloads_week>0</downloads_week><downloads_day>0</downloads_day><raw_size>-1</raw_size><raw_downloads>136</raw_downloads><raw_downloads_month>0</raw_downloads_month><raw_downloads_week>0</raw_downloads_week><raw_downloads_day>0</raw_downloads_day></version><version><id>747092018</id><name>sha256:db2e42cf9539bd89da23ef0c1060f57920ad7aadab66b8e59b571d6cb1c8b616</name><date>2026-04-23</date><newest>false</newest><latest>false</latest><size>515.8 MB</size><downloads>82</downloads><downloads_month>8</downloads_month><downloads_week>0</downloads_week><downloads_day>0</downloads_day><raw_size>515836866</raw_size><raw_downloads>82</raw_downloads><raw_downloads_month>8</raw_downloads_month><raw_downloads_week>0</raw_downloads_week><raw_downloads_day>0</raw_downloads_day></version><version><id>747092022</id><name>sha256:b4f666642e76f2eebcc6fd3d1be157dd52681102f36270f19f40ef3c6b0f2da2</name><date>2026-04-23</date><newest>false</newest><latest>false</latest><size>9.1 kB</size><downloads>3</downloads><downloads_month>2</downloads_month><downloads_week>0</downloads_week><downloads_day>0</downloads_day><raw_size>9198</raw_size><raw_downloads>3</raw_downloads><raw_downloads_month>2</raw_downloads_month><raw_downloads_week>0</raw_downloads_week><raw_downloads_day>0</raw_downloads_day></version><version><id>747092027</id><name>sha256:735d9b34b0f605a5f175bcd83b47da324fb2edd5fae62d25ec82616713d0a3ea</name><date>2026-04-23</date><newest>false</newest><latest>false</latest><size>-1</size><downloads>86</downloads><downloads_month>8</downloads_month><downloads_week>0</downloads_week><downloads_day>0</downloads_day><raw_size>-1</raw_size><raw_downloads>86</raw_downloads><raw_downloads_month>8</raw_downloads_month><raw_downloads_week>0</raw_downloads_week><raw_downloads_day>0</raw_downloads_day></version><version><id>757582890</id><name>sha256:d14907add116f8da7bcc706422facc43e1d938bd884231e6bcc75e0001b32df6</name><date>2026-04-23</date><newest>false</newest><latest>false</latest><size>515.8 MB</size><downloads>22</downloads><downloads_month>22</downloads_month><downloads_week>0</downloads_week><downloads_day>0</downloads_day><raw_size>515836860</raw_size><raw_downloads>22</raw_downloads><raw_downloads_month>22</raw_downloads_month><raw_downloads_week>0</raw_downloads_week><raw_downloads_day>0</raw_downloads_day></version><version><id>757582904</id><name>sha256:50cdb7808954f8140a5ce7a2135cd9ffbb4d49bc0b15bdac0749902007c985d6</name><date>2026-04-23</date><newest>false</newest><latest>false</latest><size>13 kB</size><downloads>3</downloads><downloads_month>3</downloads_month><downloads_week>0</downloads_week><downloads_day>0</downloads_day><raw_size>13005</raw_size><raw_downloads>3</raw_downloads><raw_downloads_month>3</raw_downloads_month><raw_downloads_week>0</raw_downloads_week><raw_downloads_day>0</raw_downloads_day></version><version><id>757582921</id><name>sha256:3b366fe69077a24de0e1d96690b95cc2f0a652c1c31620dcf38d0fdfbc9805e4</name><date>2026-04-23</date><newest>false</newest><latest>false</latest><size>-1</size><downloads>22</downloads><downloads_month>22</downloads_month><downloads_week>0</downloads_week><downloads_day>0</downloads_day><raw_size>-1</raw_size><raw_downloads>22</raw_downloads><raw_downloads_month>22</raw_downloads_month><raw_downloads_week>0</raw_downloads_week><raw_downloads_day>0</raw_downloads_day></version><version><id>760796965</id><name>sha256:b74862271219a4233413e38c0915be8e75e2fe9d91ea7f4a2e2f32ceae84c936</name><date>2026-04-23</date><newest>false</newest><latest>false</latest><size>515.8 MB</size><downloads>174</downloads><downloads_month>174</downloads_month><downloads_week>0</downloads_week><downloads_day>0</downloads_day><raw_size>515836866</raw_size><raw_downloads>174</raw_downloads><raw_downloads_month>174</raw_downloads_month><raw_downloads_week>0</raw_downloads_week><raw_downloads_day>0</raw_downloads_day></version><version><id>760796969</id><name>sha256:06e747b36e452f618601e1d911f8c79d807eb8b2f949e231484323176999a71d</name><date>2026-04-23</date><newest>false</newest><latest>false</latest><size>9.1 kB</size><downloads>3</downloads><downloads_month>3</downloads_month><downloads_week>0</downloads_week><downloads_day>0</downloads_day><raw_size>9198</raw_size><raw_downloads>3</raw_downloads><raw_downloads_month>3</raw_downloads_month><raw_downloads_week>0</raw_downloads_week><raw_downloads_day>0</raw_downloads_day></version><version><id>760796974</id><name>sha256:6c8c05343cef3858ca3cdb4097e497581ce9c58e5753750448a97ac65cd0041e</name><date>2026-04-23</date><newest>false</newest><latest>false</latest><size>-1</size><downloads>176</downloads><downloads_month>176</downloads_month><downloads_week>0</downloads_week><downloads_day>0</downloads_day><raw_size>-1</raw_size><raw_downloads>176</raw_downloads><raw_downloads_month>176</raw_downloads_month><raw_downloads_week>0</raw_downloads_week><raw_downloads_day>0</raw_downloads_day></version><version><id>774703577</id><name>sha256:5b776e00854fcb1cbab76027a642dfbab17065d63c7e0a7477d59570e69acb1a</name><date>2026-04-23</date><newest>false</newest><latest>false</latest><size>515.8 MB</size><downloads>74</downloads><downloads_month>74</downloads_month><downloads_week>0</downloads_week><downloads_day>0</downloads_day><raw_size>515836866</raw_size><raw_downloads>74</raw_downloads><raw_downloads_month>74</raw_downloads_month><raw_downloads_week>0</raw_downloads_week><raw_downloads_day>0</raw_downloads_day></version><version><id>774703579</id><name>sha256:01955e930fc81ff9d05a0251d9ecbd4e3a647426c0ce9c4bb8b17ad9da5c117c</name><date>2026-04-23</date><newest>false</newest><latest>false</latest><size>9.1 kB</size><downloads>3</downloads><downloads_month>3</downloads_month><downloads_week>0</downloads_week><downloads_day>0</downloads_day><raw_size>9198</raw_size><raw_downloads>3</raw_downloads><raw_downloads_month>3</raw_downloads_month><raw_downloads_week>0</raw_downloads_week><raw_downloads_day>0</raw_downloads_day></version><version><id>774703588</id><name>sha256:07cbed8def31263f869b198edd0579aac4cdf58c7db8add4bf3b4ee621b1007f</name><date>2026-04-23</date><newest>false</newest><latest>false</latest><size>-1</size><downloads>74</downloads><downloads_month>74</downloads_month><downloads_week>0</downloads_week><downloads_day>0</downloads_day><raw_size>-1</raw_size><raw_downloads>74</raw_downloads><raw_downloads_month>74</raw_downloads_month><raw_downloads_week>0</raw_downloads_week><raw_downloads_day>0</raw_downloads_day></version><version><id>788085083</id><name>sha256:9daede600c50ad05f723f6e079dea4931ad57c80565f4a15b0ca2baa5c73b238</name><date>2026-04-23</date><newest>false</newest><latest>false</latest><size>515.8 MB</size><downloads>172</downloads><downloads_month>172</downloads_month><downloads_week>2</downloads_week><downloads_day>0</downloads_day><raw_size>515836866</raw_size><raw_downloads>172</raw_downloads><raw_downloads_month>172</raw_downloads_month><raw_downloads_week>2</raw_downloads_week><raw_downloads_day>0</raw_downloads_day></version><version><id>788085091</id><name>sha256:34b963564883e933452dbce4ed68808022539ef130066a0b4fb673ea2944fbe4</name><date>2026-04-23</date><newest>false</newest><latest>false</latest><size>9.1 kB</size><downloads>3</downloads><downloads_month>3</downloads_month><downloads_week>2</downloads_week><downloads_day>0</downloads_day><raw_size>9198</raw_size><raw_downloads>3</raw_downloads><raw_downloads_month>3</raw_downloads_month><raw_downloads_week>2</raw_downloads_week><raw_downloads_day>0</raw_downloads_day></version><version><id>788085097</id><name>sha256:508ff7cc3cd2a0b1595234a9d53f19d2ba016afc373e4968d2e5ebd5d1cbf748</name><date>2026-04-23</date><newest>false</newest><latest>false</latest><size>-1</size><downloads>172</downloads><downloads_month>172</downloads_month><downloads_week>2</downloads_week><downloads_day>0</downloads_day><raw_size>-1</raw_size><raw_downloads>172</raw_downloads><raw_downloads_month>172</raw_downloads_month><raw_downloads_week>2</raw_downloads_week><raw_downloads_day>0</raw_downloads_day></version><version><id>802881333</id><name>sha256:4699a580c8ca009e256a8ed5c67374f2afd4ec228c1d201acf36ad23af71793e</name><date>2026-04-23</date><newest>false</newest><latest>false</latest><size>515.8 MB</size><downloads>146</downloads><downloads_month>146</downloads_month><downloads_week>146</downloads_week><downloads_day>3</downloads_day><raw_size>515836866</raw_size><raw_downloads>146</raw_downloads><raw_downloads_month>146</raw_downloads_month><raw_downloads_week>146</raw_downloads_week><raw_downloads_day>3</raw_downloads_day></version><version><id>802881337</id><name>sha256:097cf0d66efd82aa921e24f0098f4399f3c2686abf4c3f7ebe3954b86623969e</name><date>2026-04-23</date><newest>false</newest><latest>false</latest><size>9.1 kB</size><downloads>2</downloads><downloads_month>2</downloads_month><downloads_week>2</downloads_week><downloads_day>2</downloads_day><raw_size>9197</raw_size><raw_downloads>2</raw_downloads><raw_downloads_month>2</raw_downloads_month><raw_downloads_week>2</raw_downloads_week><raw_downloads_day>2</raw_downloads_day></version><version><id>802881342</id><name>sha256:61487db421820d5a0445b7851453aa26e512c3f29fde0c0df33e3bc37f488447</name><date>2026-04-23</date><newest>false</newest><latest>false</latest><size>-1</size><downloads>146</downloads><downloads_month>146</downloads_month><downloads_week>146</downloads_week><downloads_day>3</downloads_day><raw_size>-1</raw_size><raw_downloads>146</raw_downloads><raw_downloads_month>146</raw_downloads_month><raw_downloads_week>146</raw_downloads_week><raw_downloads_day>3</raw_downloads_day></version><version><id>815802267</id><name>sha256:ca94f39cc6cf11e8b5a0f8b89c7d711c4edc7017043e195c69cf6e19d8294ad0</name><date>2026-04-23</date><newest>false</newest><latest>false</latest><size>515.8 MB</size><downloads>12</downloads><downloads_month>12</downloads_month><downloads_week>12</downloads_week><downloads_day>12</downloads_day><raw_size>515836860</raw_size><raw_downloads>12</raw_downloads><raw_downloads_month>12</raw_downloads_month><raw_downloads_week>12</raw_downloads_week><raw_downloads_day>12</raw_downloads_day></version><version><id>815802275</id><name>sha256:c43d0659f5e320bf4626a76e7c7d69ab2798fba28be8698ae71c3cabb050f013</name><date>2026-04-23</date><newest>false</newest><latest>false</latest><size>17.2 kB</size><downloads>0</downloads><downloads_month>0</downloads_month><downloads_week>0</downloads_week><downloads_day>0</downloads_day><raw_size>17288</raw_size><raw_downloads>0</raw_downloads><raw_downloads_month>0</raw_downloads_month><raw_downloads_week>0</raw_downloads_week><raw_downloads_day>0</raw_downloads_day></version><version><id>815802285</id><name>sha256:1a752e5fe03130d1e0be200cfc5d7f30c47914a4ef9c19a757c127e5c556c7d8</name><date>2026-04-23</date><newest>true</newest><latest>false</latest><size>-1</size><downloads>12</downloads><downloads_month>12</downloads_month><downloads_week>12</downloads_week><downloads_day>12</downloads_day><raw_size>-1</raw_size><raw_downloads>12</raw_downloads><raw_downloads_month>12</raw_downloads_month><raw_downloads_week>12</raw_downloads_week><raw_downloads_day>12</raw_downloads_day><tags>edge</tags><tags>main</tags></version>
</xml>