<?xml version="1.0" encoding="UTF-8"?><xml><owner_type>orgs</owner_type><package_type>container</package_type><owner_id>63878</owner_id><owner>sanger</owner><repo>wrangler</repo><package>samples_extraction%2Fsamples_extraction</package><date>2026-04-28</date><size>713 MB</size><versions>30</versions><tagged>11</tagged><owner_rank>11</owner_rank><repo_rank>1</repo_rank><downloads>3.6k</downloads><downloads_month>89</downloads_month><downloads_week>10</downloads_week><downloads_day>-1</downloads_day><raw_size>713069252</raw_size><raw_versions>30</raw_versions><raw_tagged>11</raw_tagged><raw_owner_rank>11</raw_owner_rank><raw_repo_rank>1</raw_repo_rank><raw_downloads>3626</raw_downloads><raw_downloads_month>89</raw_downloads_month><raw_downloads_week>10</raw_downloads_week><raw_downloads_day>-1</raw_downloads_day><version><id>102730544</id><name>sha256:0d53d12a5ca31309d7b6c7ff04d3db5cfc4e5909d71530729ca09ebe1f45e81c</name><date>2026-04-28</date><newest>false</newest><latest>false</latest><size>748.5 MB</size><downloads>160</downloads><downloads_month>8</downloads_month><downloads_week>1</downloads_week><downloads_day>0</downloads_day><raw_size>748542502</raw_size><raw_downloads>160</raw_downloads><raw_downloads_month>8</raw_downloads_month><raw_downloads_week>1</raw_downloads_week><raw_downloads_day>0</raw_downloads_day><tags>dpl-785-remove-old-releases</tags></version><version><id>117127036</id><name>sha256:f6fbc9b12913ea6f62f768c661da2c16aac292406fa6968559482020e6756d61</name><date>2026-04-28</date><newest>false</newest><latest>false</latest><size>748.3 MB</size><downloads>132</downloads><downloads_month>8</downloads_month><downloads_week>1</downloads_week><downloads_day>0</downloads_day><raw_size>748301460</raw_size><raw_downloads>132</raw_downloads><raw_downloads_month>8</raw_downloads_month><raw_downloads_week>1</raw_downloads_week><raw_downloads_day>0</raw_downloads_day><tags>uat-mysql-upgrade</tags></version><version><id>120120518</id><name>sha256:d90e2516d9d4b8071cd4c95af5427839bc6103120033d46748f04d9c6451685e</name><date>2026-04-28</date><newest>false</newest><latest>false</latest><size>748.3 MB</size><downloads>153</downloads><downloads_month>8</downloads_month><downloads_week>1</downloads_week><downloads_day>0</downloads_day><raw_size>748363861</raw_size><raw_downloads>153</raw_downloads><raw_downloads_month>8</raw_downloads_month><raw_downloads_week>1</raw_downloads_week><raw_downloads_day>0</raw_downloads_day><tags>release-2.2.0</tags></version><version><id>157167193</id><name>sha256:f3984e84e09199bbe939baafa537129784493ff0e8e51328feb7cb1a304a07f2</name><date>2026-04-28</date><newest>false</newest><latest>false</latest><size>-1</size><downloads>-1</downloads><downloads_month>-1</downloads_month><downloads_week>-1</downloads_week><downloads_day>-1</downloads_day><raw_size>-1</raw_size><raw_downloads>-1</raw_downloads><raw_downloads_month>-1</raw_downloads_month><raw_downloads_week>-1</raw_downloads_week><raw_downloads_day>-1</raw_downloads_day><tags>release-2.2.1</tags></version><version><id>164696805</id><name>sha256:b36f9f51a2825df59bf37f192ae1046434b1fdbda2521ea62ae67a5172afe46e</name><date>2026-04-28</date><newest>false</newest><latest>false</latest><size>748.6 MB</size><downloads>80</downloads><downloads_month>8</downloads_month><downloads_week>1</downloads_week><downloads_day>0</downloads_day><raw_size>748627870</raw_size><raw_downloads>80</raw_downloads><raw_downloads_month>8</raw_downloads_month><raw_downloads_week>1</raw_downloads_week><raw_downloads_day>0</raw_downloads_day><tags>uat-dpl-1003-2</tags></version><version><id>196057079</id><name>sha256:0b1b94abaef8748696d81c67312dfa4477a67ace1edd4a9a6992b1104ae1b481</name><date>2026-04-28</date><newest>false</newest><latest>false</latest><size>750.8 MB</size><downloads>42</downloads><downloads_month>8</downloads_month><downloads_week>1</downloads_week><downloads_day>0</downloads_day><raw_size>750891199</raw_size><raw_downloads>42</raw_downloads><raw_downloads_month>8</raw_downloads_month><raw_downloads_week>1</raw_downloads_week><raw_downloads_day>0</raw_downloads_day><tags>release-2.2.3</tags></version><version><id>196079547</id><name>sha256:e92ecf41e618b6c316d17f041c4c0df62b7acbd155e7cd43a9221683d78f713d</name><date>2026-04-28</date><newest>false</newest><latest>false</latest><size>750.8 MB</size><downloads>51</downloads><downloads_month>8</downloads_month><downloads_week>1</downloads_week><downloads_day>0</downloads_day><raw_size>750897215</raw_size><raw_downloads>51</raw_downloads><raw_downloads_month>8</raw_downloads_month><raw_downloads_week>1</raw_downloads_week><raw_downloads_day>0</raw_downloads_day><tags>release-2.2.4</tags></version><version><id>204624062</id><name>sha256:14c80959f5577eee6c329e7b7fc4bc114d29324c09489e9aae82dc5ea45142f8</name><date>2026-04-28</date><newest>false</newest><latest>false</latest><size>725.7 MB</size><downloads>56</downloads><downloads_month>8</downloads_month><downloads_week>1</downloads_week><downloads_day>0</downloads_day><raw_size>725743612</raw_size><raw_downloads>56</raw_downloads><raw_downloads_month>8</raw_downloads_month><raw_downloads_week>1</raw_downloads_week><raw_downloads_day>0</raw_downloads_day><tags>release-2.2.5</tags></version><version><id>273283397</id><name>sha256:b1953c0d581eff652a9bc5e8b5dc695577fa0d6f891a7f98524494cedfd857ea</name><date>2026-04-28</date><newest>false</newest><latest>false</latest><size>727.6 MB</size><downloads>18</downloads><downloads_month>8</downloads_month><downloads_week>1</downloads_week><downloads_day>0</downloads_day><raw_size>727622713</raw_size><raw_downloads>18</raw_downloads><raw_downloads_month>8</raw_downloads_month><raw_downloads_week>1</raw_downloads_week><raw_downloads_day>0</raw_downloads_day><tags>uat-rails-7-upgrade</tags></version><version><id>274799234</id><name>sha256:142d4bb66d2c6ed0c62e092d6bc9abcd94a53f683a2938b88fe3ef3d1f0e1b60</name><date>2026-04-28</date><newest>false</newest><latest>true</latest><size>749.9 MB</size><downloads>27</downloads><downloads_month>18</downloads_month><downloads_week>2</downloads_week><downloads_day>0</downloads_day><raw_size>749916866</raw_size><raw_downloads>27</raw_downloads><raw_downloads_month>18</raw_downloads_month><raw_downloads_week>2</raw_downloads_week><raw_downloads_day>0</raw_downloads_day><tags>latest</tags><tags>master</tags></version><version><id>376736097</id><name>sha256:a90baf30dc8f2b25535e3bc756ef20e065458870196c06fa2a5ff92e7d5e353c</name><date>2026-04-28</date><newest>false</newest><latest>false</latest><size>731.3 MB</size><downloads>2</downloads><downloads_month>0</downloads_month><downloads_week>0</downloads_week><downloads_day>0</downloads_day><raw_size>731307728</raw_size><raw_downloads>2</raw_downloads><raw_downloads_month>0</raw_downloads_month><raw_downloads_week>0</raw_downloads_week><raw_downloads_day>0</raw_downloads_day></version><version><id>376736197</id><name>sha256:ab1ce4d37dc169cfe372a8cd6e01f6ec45964b259342f28bbf4eece0a5792a14</name><date>2026-04-28</date><newest>false</newest><latest>false</latest><size>731.3 MB</size><downloads>2</downloads><downloads_month>0</downloads_month><downloads_week>0</downloads_week><downloads_day>0</downloads_day><raw_size>731302777</raw_size><raw_downloads>2</raw_downloads><raw_downloads_month>0</raw_downloads_month><raw_downloads_week>0</raw_downloads_week><raw_downloads_day>0</raw_downloads_day></version><version><id>377198225</id><name>sha256:8ad0affa540bf855e1527f04d6b267f952f3a0e5df541e49baee53266b815ee4</name><date>2026-04-28</date><newest>false</newest><latest>false</latest><size>710.7 MB</size><downloads>2</downloads><downloads_month>0</downloads_month><downloads_week>0</downloads_week><downloads_day>0</downloads_day><raw_size>710793201</raw_size><raw_downloads>2</raw_downloads><raw_downloads_month>0</raw_downloads_month><raw_downloads_week>0</raw_downloads_week><raw_downloads_day>0</raw_downloads_day></version><version><id>377198554</id><name>sha256:d3cc8c47b9611c93f3fce3ca692114fed8dcc7fbda4d1f5177b11b7f22c5dc72</name><date>2026-04-28</date><newest>false</newest><latest>false</latest><size>710.8 MB</size><downloads>2</downloads><downloads_month>0</downloads_month><downloads_week>0</downloads_week><downloads_day>0</downloads_day><raw_size>710802789</raw_size><raw_downloads>2</raw_downloads><raw_downloads_month>0</raw_downloads_month><raw_downloads_week>0</raw_downloads_week><raw_downloads_day>0</raw_downloads_day></version><version><id>377198641</id><name>sha256:1a5483a0462a95bb4fb07a5f5f70d283594f7d9f202c3088dfeb84feed8837d2</name><date>2026-04-28</date><newest>false</newest><latest>false</latest><size>710.8 MB</size><downloads>2</downloads><downloads_month>0</downloads_month><downloads_week>0</downloads_week><downloads_day>0</downloads_day><raw_size>710805026</raw_size><raw_downloads>2</raw_downloads><raw_downloads_month>0</raw_downloads_month><raw_downloads_week>0</raw_downloads_week><raw_downloads_day>0</raw_downloads_day></version><version><id>377200048</id><name>sha256:77ba6efabd31d3e149c893e37d2fb90c0977eeceb04a135f60b797181977ceef</name><date>2026-04-28</date><newest>false</newest><latest>false</latest><size>710.8 MB</size><downloads>2</downloads><downloads_month>0</downloads_month><downloads_week>0</downloads_week><downloads_day>0</downloads_day><raw_size>710806218</raw_size><raw_downloads>2</raw_downloads><raw_downloads_month>0</raw_downloads_month><raw_downloads_week>0</raw_downloads_week><raw_downloads_day>0</raw_downloads_day></version><version><id>377200889</id><name>sha256:0f6e8d0932a958f3b6977542203928337a3147d046fdaf276e7f31eed9b281f1</name><date>2026-04-28</date><newest>false</newest><latest>false</latest><size>710.8 MB</size><downloads>2</downloads><downloads_month>0</downloads_month><downloads_week>0</downloads_week><downloads_day>0</downloads_day><raw_size>710806267</raw_size><raw_downloads>2</raw_downloads><raw_downloads_month>0</raw_downloads_month><raw_downloads_week>0</raw_downloads_week><raw_downloads_day>0</raw_downloads_day></version><version><id>377201220</id><name>sha256:0dbf5378da09608a43dc94951ebe59e53426046d402fe4e0777dd31183c30e03</name><date>2026-04-28</date><newest>false</newest><latest>false</latest><size>712.3 MB</size><downloads>2</downloads><downloads_month>0</downloads_month><downloads_week>0</downloads_week><downloads_day>0</downloads_day><raw_size>712307425</raw_size><raw_downloads>2</raw_downloads><raw_downloads_month>0</raw_downloads_month><raw_downloads_week>0</raw_downloads_week><raw_downloads_day>0</raw_downloads_day></version><version><id>377217771</id><name>sha256:0c925600263558af2af51bf7afcd2d5d2b331c99bfef674b20af6366741db201</name><date>2026-04-28</date><newest>false</newest><latest>false</latest><size>712.3 MB</size><downloads>2</downloads><downloads_month>0</downloads_month><downloads_week>0</downloads_week><downloads_day>0</downloads_day><raw_size>712303647</raw_size><raw_downloads>2</raw_downloads><raw_downloads_month>0</raw_downloads_month><raw_downloads_week>0</raw_downloads_week><raw_downloads_day>0</raw_downloads_day></version><version><id>381215886</id><name>sha256:81dbe14687ac940d840bc814e990cb228a8941e63c014cacde8d65187046d03b</name><date>2026-04-28</date><newest>false</newest><latest>false</latest><size>712.3 MB</size><downloads>2</downloads><downloads_month>0</downloads_month><downloads_week>0</downloads_week><downloads_day>0</downloads_day><raw_size>712381668</raw_size><raw_downloads>2</raw_downloads><raw_downloads_month>0</raw_downloads_month><raw_downloads_week>0</raw_downloads_week><raw_downloads_day>0</raw_downloads_day></version><version><id>385972781</id><name>sha256:349179142d811849b41898397d2134f7050164a4ab1e2b80fe17e7b191aa086a</name><date>2026-04-28</date><newest>false</newest><latest>false</latest><size>712.4 MB</size><downloads>2</downloads><downloads_month>0</downloads_month><downloads_week>0</downloads_week><downloads_day>0</downloads_day><raw_size>712435399</raw_size><raw_downloads>2</raw_downloads><raw_downloads_month>0</raw_downloads_month><raw_downloads_week>0</raw_downloads_week><raw_downloads_day>0</raw_downloads_day></version><version><id>419375128</id><name>sha256:8727fced15cde2cee762099051743e1c2fcb0e91733b589b4c752bb11a85ff14</name><date>2026-04-28</date><newest>false</newest><latest>false</latest><size>712.5 MB</size><downloads>2</downloads><downloads_month>0</downloads_month><downloads_week>0</downloads_week><downloads_day>0</downloads_day><raw_size>712539266</raw_size><raw_downloads>2</raw_downloads><raw_downloads_month>0</raw_downloads_month><raw_downloads_week>0</raw_downloads_week><raw_downloads_day>0</raw_downloads_day></version><version><id>419375253</id><name>sha256:91d4d665aa6c08c96941de88c59a991b31d5e354c430062640653c782ce2a54a</name><date>2026-04-28</date><newest>false</newest><latest>false</latest><size>712.3 MB</size><downloads>2</downloads><downloads_month>0</downloads_month><downloads_week>0</downloads_week><downloads_day>0</downloads_day><raw_size>712322708</raw_size><raw_downloads>2</raw_downloads><raw_downloads_month>0</raw_downloads_month><raw_downloads_week>0</raw_downloads_week><raw_downloads_day>0</raw_downloads_day></version><version><id>419375640</id><name>sha256:f017e38778982b4ecb51a25c2c07d7cbf6cc86e7a365b67b81ddc3dd304724ef</name><date>2026-04-28</date><newest>false</newest><latest>false</latest><size>712.3 MB</size><downloads>2</downloads><downloads_month>0</downloads_month><downloads_week>0</downloads_week><downloads_day>0</downloads_day><raw_size>712321200</raw_size><raw_downloads>2</raw_downloads><raw_downloads_month>0</raw_downloads_month><raw_downloads_week>0</raw_downloads_week><raw_downloads_day>0</raw_downloads_day></version><version><id>419375919</id><name>sha256:24a01be8155790df8bd99747ab2c95507a45e0cd32bdedd01e5a05560df8467c</name><date>2026-04-28</date><newest>false</newest><latest>false</latest><size>712.3 MB</size><downloads>2</downloads><downloads_month>0</downloads_month><downloads_week>0</downloads_week><downloads_day>0</downloads_day><raw_size>712326637</raw_size><raw_downloads>2</raw_downloads><raw_downloads_month>0</raw_downloads_month><raw_downloads_week>0</raw_downloads_week><raw_downloads_day>0</raw_downloads_day></version><version><id>419376953</id><name>sha256:89b2b498ca7c902626f42d4fa6d95ec95e073c69129cf681440e1dc54bb3fa80</name><date>2026-04-28</date><newest>false</newest><latest>false</latest><size>712.3 MB</size><downloads>2</downloads><downloads_month>0</downloads_month><downloads_week>0</downloads_week><downloads_day>0</downloads_day><raw_size>712333429</raw_size><raw_downloads>2</raw_downloads><raw_downloads_month>0</raw_downloads_month><raw_downloads_week>0</raw_downloads_week><raw_downloads_day>0</raw_downloads_day></version><version><id>419377351</id><name>sha256:2089e685dde9f653d95af14f5e32c1d2279e489692501b15ff766b1320388816</name><date>2026-04-28</date><newest>false</newest><latest>false</latest><size>712.3 MB</size><downloads>2</downloads><downloads_month>0</downloads_month><downloads_week>0</downloads_week><downloads_day>0</downloads_day><raw_size>712340394</raw_size><raw_downloads>2</raw_downloads><raw_downloads_month>0</raw_downloads_month><raw_downloads_week>0</raw_downloads_week><raw_downloads_day>0</raw_downloads_day></version><version><id>419377768</id><name>sha256:3443101c43b735060f5a057f93b72e0c9223f911b170f24296181e9e50c114fc</name><date>2026-04-28</date><newest>false</newest><latest>false</latest><size>712.3 MB</size><downloads>2</downloads><downloads_month>0</downloads_month><downloads_week>0</downloads_week><downloads_day>0</downloads_day><raw_size>712327378</raw_size><raw_downloads>2</raw_downloads><raw_downloads_month>0</raw_downloads_month><raw_downloads_week>0</raw_downloads_week><raw_downloads_day>0</raw_downloads_day></version><version><id>424553116</id><name>sha256:b521d1a46806545558ed16b67c0c371d4ec80237af1d0eaf0e7891936205a14b</name><date>2026-04-28</date><newest>false</newest><latest>false</latest><size>712.4 MB</size><downloads>2</downloads><downloads_month>0</downloads_month><downloads_week>0</downloads_week><downloads_day>0</downloads_day><raw_size>712437509</raw_size><raw_downloads>2</raw_downloads><raw_downloads_month>0</raw_downloads_month><raw_downloads_week>0</raw_downloads_week><raw_downloads_day>0</raw_downloads_day></version><version><id>441387482</id><name>sha256:dd93cd7f868e4eae0ebc6f0f8bef9413e6ed8100f923822e921974f66a7f3a77</name><date>2026-04-28</date><newest>true</newest><latest>false</latest><size>713 MB</size><downloads>14</downloads><downloads_month>8</downloads_month><downloads_week>1</downloads_week><downloads_day>0</downloads_day><raw_size>713069252</raw_size><raw_downloads>14</raw_downloads><raw_downloads_month>8</raw_downloads_month><raw_downloads_week>1</raw_downloads_week><raw_downloads_day>0</raw_downloads_day><tags>develop</tags></version>
</xml>