<?xml version="1.0" encoding="UTF-8"?><xml><owner_type>users</owner_type><package_type>container</package_type><owner_id>47974576</owner_id><owner>eddycharly</owner><repo>signatures</repo><package>signatures</package><date>2026-07-12</date><size>635</size><versions>2</versions><tagged>2</tagged><owner_rank>10</owner_rank><repo_rank>1</repo_rank><downloads>375</downloads><downloads_month>2</downloads_month><downloads_week>2</downloads_week><downloads_day>0</downloads_day><raw_size>635</raw_size><raw_versions>2</raw_versions><raw_tagged>2</raw_tagged><raw_owner_rank>10</raw_owner_rank><raw_repo_rank>1</raw_repo_rank><raw_downloads>375</raw_downloads><raw_downloads_month>2</raw_downloads_month><raw_downloads_week>2</raw_downloads_week><raw_downloads_day>0</raw_downloads_day><version><id>39171292</id><name>sha256:dd6fd5e32fed772a8085ffdf933cb7e9d2b13ce99efffc030abac29bef4c8e83</name><date>2026-07-12</date><newest>false</newest><latest>false</latest><size>644</size><downloads>185</downloads><downloads_month>1</downloads_month><downloads_week>1</downloads_week><downloads_day>0</downloads_day><raw_size>644</raw_size><raw_downloads>185</raw_downloads><raw_downloads_month>1</raw_downloads_month><raw_downloads_week>1</raw_downloads_week><raw_downloads_day>0</raw_downloads_day><tags>sha256-fed22e616dfd244422d000b371f3dbf80a81c55b79d55082114f9c7b0a5e1642.sig</tags></version><version><id>39171484</id><name>sha256:1c045d1d2750bf3867b12500c44617c43266bbb1ae0767f0905f2291c178105e</name><date>2026-07-12</date><newest>true</newest><latest>true</latest><size>635</size><downloads>190</downloads><downloads_month>1</downloads_month><downloads_week>1</downloads_week><downloads_day>0</downloads_day><raw_size>635</raw_size><raw_downloads>190</raw_downloads><raw_downloads_month>1</raw_downloads_month><raw_downloads_week>1</raw_downloads_week><raw_downloads_day>0</raw_downloads_day><tags>sha256-0558eb33c6a4be9cb667353269cb705df44c13e09ccaab49102eacd6e0c6cad7.sig</tags></version></xml>